{
  "icao24": "a20930",
  "callsign": "ASA1053",
  "dep_airport_icao": "PHNL",
  "dep_airport_name": "Daniel K Inouye International Airport",
  "dep_country": "US",
  "dep_lat": 21.317825,
  "dep_lon": -157.92025,
  "arr_airport_icao": "PHHI",
  "arr_airport_name": "Wheeler Army Air Field",
  "arr_country": "US",
  "arr_lat": 21.481444,
  "arr_lon": -158.037833,
  "first_seen": 1777583265,
  "last_seen": 1777584279,
  "airline": "Alaska Airlines",
  "departure_time": "2026-04-30 21:07 UTC",
  "arrival_time": "2026-04-30 21:24 UTC",
  "duration_minutes": 16,
  "duration_str": "16m",
  "distance_km": 21.9,
  "co2_kg": 377.6
}