{
  "icao24": "a7ac49",
  "callsign": "CNS325",
  "dep_airport_icao": "KBOW",
  "dep_airport_name": "Bartow Executive Airport",
  "dep_country": "US",
  "dep_lat": 27.943359,
  "dep_lon": -81.783437,
  "arr_airport_icao": "35FD",
  "arr_airport_name": "Rush Airport",
  "arr_country": "US",
  "arr_lat": 29.692333,
  "arr_lon": -82.729167,
  "first_seen": 1778000447,
  "last_seen": 1778001817,
  "airline": "CNS",
  "departure_time": "2026-05-05 17:00 UTC",
  "arrival_time": "2026-05-05 17:23 UTC",
  "duration_minutes": 22,
  "duration_str": "22m",
  "distance_km": 215.2,
  "co2_kg": 3712.1
}