{
  "icao24": "0a0088",
  "callsign": "DAH6141",
  "dep_airport_icao": "DAOY",
  "dep_airport_name": "El Bayadh Airport",
  "dep_country": "DZ",
  "dep_lat": 33.72167,
  "dep_lon": 1.0925,
  "arr_airport_icao": "DAAG",
  "arr_airport_name": "Houari Boumediene Airport",
  "arr_country": "DZ",
  "arr_lat": 36.691,
  "arr_lon": 3.21541,
  "first_seen": 1779353180,
  "last_seen": 1779356768,
  "airline": "DAH",
  "departure_time": "2026-05-21 08:46 UTC",
  "arrival_time": "2026-05-21 09:46 UTC",
  "duration_minutes": 59,
  "duration_str": "59m",
  "distance_km": 382.4,
  "co2_kg": 6595.6
}