{
  "icao24": "a7626b",
  "callsign": "EJA575",
  "dep_airport_icao": "KDPA",
  "dep_airport_name": "Dupage Airport",
  "dep_country": "US",
  "dep_lat": 41.907053,
  "dep_lon": -88.247995,
  "arr_airport_icao": "KEDN",
  "arr_airport_name": "Enterprise Municipal Airport",
  "arr_country": "US",
  "arr_lat": 31.299722,
  "arr_lon": -85.899833,
  "first_seen": 1783276951,
  "last_seen": 1783283767,
  "airline": "EJA",
  "departure_time": "2026-07-05 18:42 UTC",
  "arrival_time": "2026-07-05 20:36 UTC",
  "duration_minutes": 113,
  "duration_str": "1h 53m",
  "distance_km": 1197.8,
  "co2_kg": 20662.4
}