{
  "icao24": "a7f3e4",
  "callsign": "EJA611",
  "dep_airport_icao": "KAPA",
  "dep_airport_name": "Centennial Airport",
  "dep_country": "US",
  "dep_lat": 39.570119,
  "dep_lon": -104.849293,
  "arr_airport_icao": "KU07",
  "arr_airport_name": "Bullfrog Basin Airport",
  "arr_country": "US",
  "arr_lat": 37.545824,
  "arr_lon": -110.713199,
  "first_seen": 1776086753,
  "last_seen": 1776090488,
  "airline": "EJA",
  "departure_time": "2026-04-13 13:25 UTC",
  "arrival_time": "2026-04-13 14:28 UTC",
  "duration_minutes": 62,
  "duration_str": "1h 2m",
  "distance_km": 557.2,
  "co2_kg": 9611.8
}