{
  "icao24": "407f67",
  "callsign": "EZY91NU",
  "dep_airport_icao": "LEAL",
  "dep_airport_name": "Alicante International Airport",
  "dep_country": "ES",
  "dep_lat": 38.2822,
  "dep_lon": -0.55816,
  "arr_airport_icao": "EGKK",
  "arr_airport_name": "London Gatwick Airport",
  "arr_country": "GB",
  "arr_lat": 51.1481,
  "arr_lon": -0.19028,
  "first_seen": 1779007888,
  "last_seen": 1779016112,
  "airline": "easyJet",
  "departure_time": "2026-05-17 08:51 UTC",
  "arrival_time": "2026-05-17 11:08 UTC",
  "duration_minutes": 137,
  "duration_str": "2h 17m",
  "distance_km": 1430.9,
  "co2_kg": 24683.3
}