{
  "icao24": "408336",
  "callsign": "GNETS",
  "dep_airport_icao": "EGHC",
  "dep_airport_name": "Land's End Airport",
  "dep_country": "GB",
  "dep_lat": 50.1028,
  "dep_lon": -5.67056,
  "arr_airport_icao": "EGHQ",
  "arr_airport_name": "Newquay Cornwall Airport",
  "arr_country": "GB",
  "arr_lat": 50.4406,
  "arr_lon": -4.99541,
  "first_seen": 1783417256,
  "last_seen": 1783418478,
  "airline": "GNE",
  "departure_time": "2026-07-07 09:40 UTC",
  "arrival_time": "2026-07-07 10:01 UTC",
  "duration_minutes": 20,
  "duration_str": "20m",
  "distance_km": 60.9,
  "co2_kg": 1051.1
}