{
  "icao24": "4b1e44",
  "callsign": "HBLMA",
  "dep_airport_icao": "LSZG",
  "dep_airport_name": "Grenchen Airport",
  "dep_country": "CH",
  "dep_lat": 47.1816,
  "dep_lon": 7.41719,
  "arr_airport_icao": "LSZG",
  "arr_airport_name": "Grenchen Airport",
  "arr_country": "CH",
  "arr_lat": 47.1816,
  "arr_lon": 7.41719,
  "first_seen": 1776947770,
  "last_seen": 1776949931,
  "airline": "HBL",
  "departure_time": "2026-04-23 12:36 UTC",
  "arrival_time": "2026-04-23 13:12 UTC",
  "duration_minutes": 36,
  "duration_str": "36m",
  "distance_km": 0.0,
  "co2_kg": 0.0
}