{
  "icao24": "0acb85",
  "callsign": "HK4712",
  "dep_airport_icao": "SKMD",
  "dep_airport_name": "Enrique Olaya Herrera Airport",
  "dep_country": "CO",
  "dep_lat": 6.22055,
  "dep_lon": -75.59058,
  "arr_airport_icao": "SKMD",
  "arr_airport_name": "Enrique Olaya Herrera Airport",
  "arr_country": "CO",
  "arr_lat": 6.22055,
  "arr_lon": -75.59058,
  "first_seen": 1781885802,
  "last_seen": 1781886455,
  "airline": "",
  "departure_time": "2026-06-19 16:16 UTC",
  "arrival_time": "2026-06-19 16:27 UTC",
  "duration_minutes": 10,
  "duration_str": "10m",
  "distance_km": 0.0,
  "co2_kg": 0.0
}