{
  "icao24": "48ae83",
  "callsign": "LOT171",
  "dep_airport_icao": "EPWA",
  "dep_airport_name": "Warsaw Chopin Airport",
  "dep_country": "PL",
  "dep_lat": 52.1657,
  "dep_lon": 20.9671,
  "arr_airport_icao": "EPDE",
  "arr_airport_name": "Deblin Military Air Base",
  "arr_country": "PL",
  "arr_lat": 51.5514,
  "arr_lon": 21.8936,
  "first_seen": 1780911260,
  "last_seen": 1780911883,
  "airline": "LOT Polish Airlines",
  "departure_time": "2026-06-08 09:34 UTC",
  "arrival_time": "2026-06-08 09:44 UTC",
  "duration_minutes": 10,
  "duration_str": "10m",
  "distance_km": 93.3,
  "co2_kg": 1610.3
}