{
  "icao24": "5001e5",
  "callsign": "MEA252",
  "dep_airport_icao": "LGAV",
  "dep_airport_name": "Eleftherios Venizelos International Airport",
  "dep_country": "GR",
  "dep_lat": 37.9364,
  "dep_lon": 23.9445,
  "arr_airport_icao": "OLRA",
  "arr_airport_name": "Rayak Air Base",
  "arr_country": "LB",
  "arr_lat": 33.8508,
  "arr_lon": 35.9877,
  "first_seen": 1784281337,
  "last_seen": 1784286151,
  "airline": "Middle East Airlines",
  "departure_time": "2026-07-17 09:42 UTC",
  "arrival_time": "2026-07-17 11:02 UTC",
  "duration_minutes": 80,
  "duration_str": "1h 20m",
  "distance_km": 1175.0,
  "co2_kg": 20267.9
}