{
  "icao24": "a1b9f6",
  "callsign": "N210ER",
  "dep_airport_icao": "MMPB",
  "dep_airport_name": "Hermanos Serdan International Airport",
  "dep_country": "MX",
  "dep_lat": 19.1581,
  "dep_lon": -98.3714,
  "arr_airport_icao": "MMSM",
  "arr_airport_name": "Santa Lucia Air Force Base",
  "arr_country": "MX",
  "arr_lat": 19.7553,
  "arr_lon": -99.0164,
  "first_seen": 1776347482,
  "last_seen": 1776348249,
  "airline": "",
  "departure_time": "2026-04-16 13:51 UTC",
  "arrival_time": "2026-04-16 14:04 UTC",
  "duration_minutes": 12,
  "duration_str": "12m",
  "distance_km": 94.8,
  "co2_kg": 1634.9
}