{
  "icao24": "a642db",
  "callsign": "N502RF",
  "dep_airport_icao": "4VA8",
  "dep_airport_name": "Christian's Airport",
  "dep_country": "US",
  "dep_lat": 37.613756,
  "dep_lon": -77.295811,
  "arr_airport_icao": "KRIC",
  "arr_airport_name": "Richmond International Airport",
  "arr_country": "US",
  "arr_lat": 37.505181,
  "arr_lon": -77.319739,
  "first_seen": 1778711721,
  "last_seen": 1778711843,
  "airline": "",
  "departure_time": "2026-05-13 22:35 UTC",
  "arrival_time": "2026-05-13 22:37 UTC",
  "duration_minutes": 2,
  "duration_str": "2m",
  "distance_km": 12.3,
  "co2_kg": 211.4
}