{
  "icao24": "aa3776",
  "callsign": "N75776",
  "dep_airport_icao": "KU42",
  "dep_airport_name": "KU42",
  "dep_country": "",
  "dep_lat": null,
  "dep_lon": null,
  "arr_airport_icao": "KENV",
  "arr_airport_name": "Wendover Airport",
  "arr_country": "US",
  "arr_lat": 40.718725,
  "arr_lon": -114.028674,
  "first_seen": 1782400903,
  "last_seen": 1782403897,
  "airline": "",
  "departure_time": "2026-06-25 15:21 UTC",
  "arrival_time": "2026-06-25 16:11 UTC",
  "duration_minutes": 49,
  "duration_str": "49m",
  "distance_km": 0.0,
  "co2_kg": 0.0
}