{
  "icao24": "4caa59",
  "callsign": "RYR15CF",
  "dep_airport_icao": "LEZL",
  "dep_airport_name": "Sevilla Airport",
  "dep_country": "ES",
  "dep_lat": 37.418,
  "dep_lon": -5.89311,
  "arr_airport_icao": "GCLB",
  "arr_airport_name": "El Berriel Aeroc Airport",
  "arr_country": "ES",
  "arr_lat": 27.7825,
  "arr_lon": -15.5072,
  "first_seen": 1783096583,
  "last_seen": 1783103321,
  "airline": "Ryanair",
  "departure_time": "2026-07-03 16:36 UTC",
  "arrival_time": "2026-07-03 18:28 UTC",
  "duration_minutes": 112,
  "duration_str": "1h 52m",
  "distance_km": 1397.9,
  "co2_kg": 24114.4
}