{
  "icao24": "48c2a5",
  "callsign": "RYR4125",
  "dep_airport_icao": "LHBP",
  "dep_airport_name": "Budapest Ferenc Liszt International Airport",
  "dep_country": "HU",
  "dep_lat": 47.4369,
  "dep_lon": 19.2556,
  "arr_airport_icao": "LIAU",
  "arr_airport_name": "Capua Airport",
  "arr_country": "IT",
  "arr_lat": 41.116,
  "arr_lon": 14.178,
  "first_seen": 1777883203,
  "last_seen": 1777887142,
  "airline": "Ryanair",
  "departure_time": "2026-05-04 08:26 UTC",
  "arrival_time": "2026-05-04 09:32 UTC",
  "duration_minutes": 65,
  "duration_str": "1h 5m",
  "distance_km": 810.4,
  "co2_kg": 13979.1
}