{
  "icao24": "a70c23",
  "callsign": "SCU9",
  "dep_airport_icao": "KOKM",
  "dep_airport_name": "Okmulgee Regional/Paul And Betty Abbott Field",
  "dep_country": "US",
  "dep_lat": 35.668111,
  "dep_lon": -95.948528,
  "arr_airport_icao": "KOKM",
  "arr_airport_name": "Okmulgee Regional/Paul And Betty Abbott Field",
  "arr_country": "US",
  "arr_lat": 35.668111,
  "arr_lon": -95.948528,
  "first_seen": 1775161841,
  "last_seen": 1775161846,
  "airline": "SCU",
  "departure_time": "2026-04-02 20:30 UTC",
  "arrival_time": "2026-04-02 20:30 UTC",
  "duration_minutes": 0,
  "duration_str": "0m",
  "distance_km": 0.0,
  "co2_kg": 0.0
}