{
  "icao24": "ab9b81",
  "callsign": "SCX215",
  "dep_airport_icao": "KMSP",
  "dep_airport_name": "Minneapolis-St Paul International/Wold-Chamberlain Airport",
  "dep_country": "US",
  "dep_lat": 44.881972,
  "dep_lon": -93.221778,
  "arr_airport_icao": "KTPA",
  "arr_airport_name": "Tampa International Airport",
  "arr_country": "US",
  "arr_lat": 27.975469,
  "arr_lon": -82.533248,
  "first_seen": 1776715081,
  "last_seen": 1776724035,
  "airline": "SCX",
  "departure_time": "2026-04-20 19:58 UTC",
  "arrival_time": "2026-04-20 22:27 UTC",
  "duration_minutes": 149,
  "duration_str": "2h 29m",
  "distance_km": 2104.8,
  "co2_kg": 36307.2
}