{
  "icao24": "46d276",
  "callsign": "SEH6SF",
  "dep_airport_icao": "LGAV",
  "dep_airport_name": "Eleftherios Venizelos International Airport",
  "dep_country": "GR",
  "dep_lat": 37.9364,
  "dep_lon": 23.9445,
  "arr_airport_icao": "LBHT",
  "arr_airport_name": "Ihtiman Airport",
  "arr_country": "BG",
  "arr_lat": 42.42189,
  "arr_lon": 23.76722,
  "first_seen": 1781450221,
  "last_seen": 1781454696,
  "airline": "SEH",
  "departure_time": "2026-06-14 15:17 UTC",
  "arrival_time": "2026-06-14 16:31 UTC",
  "duration_minutes": 74,
  "duration_str": "1h 14m",
  "distance_km": 499.0,
  "co2_kg": 8607.6
}