{
  "icao24": "ad72a7",
  "callsign": "VTS2801",
  "dep_airport_icao": "KLRD",
  "dep_airport_name": "Laredo International Airport",
  "dep_country": "US",
  "dep_lat": 27.544194,
  "dep_lon": -99.461583,
  "arr_airport_icao": "28AZ",
  "arr_airport_name": "Sampleys Airport",
  "arr_country": "US",
  "arr_lat": 33.922807,
  "arr_lon": -113.181303,
  "first_seen": 1775900904,
  "last_seen": 1775908863,
  "airline": "VTS",
  "departure_time": "2026-04-11 09:48 UTC",
  "arrival_time": "2026-04-11 12:01 UTC",
  "duration_minutes": 132,
  "duration_str": "2h 12m",
  "distance_km": 1488.9,
  "co2_kg": 25683.2
}