[
  {
    "icao24": "008dea",
    "callsign": "SFR590",
    "dep_airport_icao": "FAOR",
    "dep_airport_name": "O. R. Tambo International Airport",
    "dep_country": "ZA",
    "dep_lat": -26.13367,
    "dep_lon": 28.24233,
    "arr_airport_icao": "FADH",
    "arr_airport_name": "Durnacol Airport",
    "arr_country": "ZA",
    "arr_lat": -28.0461,
    "arr_lon": 30.0064,
    "first_seen": 1781755984,
    "last_seen": 1781757284,
    "airline": "SFR",
    "departure_time": "2026-06-18 04:13 UTC",
    "arrival_time": "2026-06-18 04:34 UTC",
    "duration_minutes": 21,
    "duration_str": "21m",
    "distance_km": 275.2,
    "co2_kg": 4746.5
  },
  {
    "icao24": "00b089",
    "callsign": "SFR286",
    "dep_airport_icao": "FAOR",
    "dep_airport_name": "O. R. Tambo International Airport",
    "dep_country": "ZA",
    "dep_lat": -26.13367,
    "dep_lon": 28.24233,
    "arr_airport_icao": "FANC",
    "arr_airport_name": "Newcastle Airport",
    "arr_country": "ZA",
    "arr_lat": -27.7706,
    "arr_lon": 29.9769,
    "first_seen": 1781755652,
    "last_seen": 1781756904,
    "airline": "SFR",
    "departure_time": "2026-06-18 04:07 UTC",
    "arrival_time": "2026-06-18 04:28 UTC",
    "duration_minutes": 20,
    "duration_str": "20m",
    "distance_km": 250.4,
    "co2_kg": 4318.9
  },
  {
    "icao24": "0101ba",
    "callsign": "MSR024",
    "dep_airport_icao": "HECA",
    "dep_airport_name": "Cairo International Airport",
    "dep_country": "EG",
    "dep_lat": 30.1219,
    "dep_lon": 31.4056,
    "arr_airport_icao": "HESC",
    "arr_airport_name": "St Catherine International Airport",
    "arr_country": "EG",
    "arr_lat": 28.6853,
    "arr_lon": 34.0625,
    "first_seen": 1781755671,
    "last_seen": 1781756941,
    "airline": "EgyptAir",
    "departure_time": "2026-06-18 04:07 UTC",
    "arrival_time": "2026-06-18 04:29 UTC",
    "duration_minutes": 21,
    "duration_str": "21m",
    "distance_km": 302.9,
    "co2_kg": 5225.1
  },
  {
    "icao24": "0101fa",
    "callsign": "RBG599",
    "dep_airport_icao": "HECA",
    "dep_airport_name": "Cairo International Airport",
    "dep_country": "EG",
    "dep_lat": 30.1219,
    "dep_lon": 31.4056,
    "arr_airport_icao": "HE21",
    "arr_airport_name": "HE21",
    "arr_country": "",
    "arr_lat": null,
    "arr_lon": null,
    "first_seen": 1781755426,
    "last_seen": 1781756840,
    "airline": "RBG",
    "departure_time": "2026-06-18 04:03 UTC",
    "arrival_time": "2026-06-18 04:27 UTC",
    "duration_minutes": 23,
    "duration_str": "23m",
    "distance_km": 0.0,
    "co2_kg": 0.0
  },
  {
    "icao24": "040260",
    "callsign": "ETH736",
    "dep_airport_icao": "LIMC",
    "dep_airport_name": "Malpensa International Airport",
    "dep_country": "IT",
    "dep_lat": 45.6306,
    "dep_lon": 8.72811,
    "arr_airport_icao": "LSZH",
    "arr_airport_name": "Zurich Airport",
    "arr_country": "CH",
    "arr_lat": 47.4647,
    "arr_lon": 8.54917,
    "first_seen": 1781759588,
    "last_seen": 1781761944,
    "airline": "Ethiopian Airlines",
    "departure_time": "2026-06-18 05:13 UTC",
    "arrival_time": "2026-06-18 05:52 UTC",
    "duration_minutes": 39,
    "duration_str": "39m",
    "distance_km": 204.4,
    "co2_kg": 3525.9
  },
  {
    "icao24": "04c33b",
    "callsign": "5YDRY",
    "dep_airport_icao": "HKJK",
    "dep_airport_name": "Jomo Kenyatta International Airport",
    "dep_country": "KE",
    "dep_lat": -1.31924,
    "dep_lon": 36.9278,
    "arr_airport_icao": "HKNW",
    "arr_airport_name": "Nairobi Wilson Airport",
    "arr_country": "KE",
    "arr_lat": -1.32172,
    "arr_lon": 36.8148,
    "first_seen": 1781762029,
    "last_seen": 1781762066,
    "airline": "",
    "departure_time": "2026-06-18 05:53 UTC",
    "arrival_time": "2026-06-18 05:54 UTC",
    "duration_minutes": 0,
    "duration_str": "0m",
    "distance_km": 12.6,
    "co2_kg": 216.7
  },
  {
    "icao24": "06a298",
    "callsign": "GNS103",
    "dep_airport_icao": "OTBH",
    "dep_airport_name": "Al Udeid Air Base",
    "dep_country": "QA",
    "dep_lat": 25.1173,
    "dep_lon": 51.315,
    "arr_airport_icao": "OTBH",
    "arr_airport_name": "Al Udeid Air Base",
    "arr_country": "QA",
    "arr_lat": 25.1173,
    "arr_lon": 51.315,
    "first_seen": 1781759826,
    "last_seen": 1781760876,
    "airline": "GNS",
    "departure_time": "2026-06-18 05:17 UTC",
    "arrival_time": "2026-06-18 05:34 UTC",
    "duration_minutes": 17,
    "duration_str": "17m",
    "distance_km": 0.0,
    "co2_kg": 0.0
  },
  {
    "icao24": "341699",
    "callsign": "SWT1SO",
    "dep_airport_icao": "EDDK",
    "dep_airport_name": "Cologne Bonn Airport",
    "dep_country": "DE",
    "dep_lat": 50.8659,
    "dep_lon": 7.14274,
    "arr_airport_icao": "LYSP",
    "arr_airport_name": "Rudine airfield",
    "arr_country": "RS",
    "arr_lat": 44.35139,
    "arr_lon": 20.96,
    "first_seen": 1781750164,
    "last_seen": 1781759055,
    "airline": "SWT",
    "departure_time": "2026-06-18 02:36 UTC",
    "arrival_time": "2026-06-18 05:04 UTC",
    "duration_minutes": 148,
    "duration_str": "2h 28m",
    "distance_km": 1260.8,
    "co2_kg": 21748.1
  },
  {
    "icao24": "3c56f4",
    "callsign": "EWG6KW",
    "dep_airport_icao": "EDDB",
    "dep_airport_name": "Berlin Brandenburg Airport",
    "dep_country": "DE",
    "dep_lat": 52.36217,
    "dep_lon": 13.50067,
    "arr_airport_icao": "EDDK",
    "arr_airport_name": "Cologne Bonn Airport",
    "arr_country": "DE",
    "arr_lat": 50.8659,
    "arr_lon": 7.14274,
    "first_seen": 1781757655,
    "last_seen": 1781760872,
    "airline": "EWG",
    "departure_time": "2026-06-18 04:40 UTC",
    "arrival_time": "2026-06-18 05:34 UTC",
    "duration_minutes": 53,
    "duration_str": "53m",
    "distance_km": 469.3,
    "co2_kg": 8094.9
  },
  {
    "icao24": "3c66e1",
    "callsign": "DLH5KA",
    "dep_airport_icao": "EDDF",
    "dep_airport_name": "Frankfurt am Main International Airport",
    "dep_country": "DE",
    "dep_lat": 50.0264,
    "dep_lon": 8.54313,
    "arr_airport_icao": "EDQN",
    "arr_airport_name": "Neustadt/Aisch Airport",
    "arr_country": "DE",
    "arr_lat": 49.5875,
    "arr_lon": 10.5775,
    "first_seen": 1781759803,
    "last_seen": 1781761129,
    "airline": "Lufthansa",
    "departure_time": "2026-06-18 05:16 UTC",
    "arrival_time": "2026-06-18 05:38 UTC",
    "duration_minutes": 22,
    "duration_str": "22m",
    "distance_km": 153.9,
    "co2_kg": 2655.2
  },
  {
    "icao24": "4243c3",
    "callsign": "AZG922",
    "dep_airport_icao": "EDFH",
    "dep_airport_name": "Frankfurt-Hahn Airport",
    "dep_country": "DE",
    "dep_lat": 49.9487,
    "dep_lon": 7.26389,
    "arr_airport_icao": "VMMC",
    "arr_airport_name": "Macau International Airport",
    "arr_country": "MO",
    "arr_lat": 22.1496,
    "arr_lon": 113.592,
    "first_seen": 1781698626,
    "last_seen": 1781760516,
    "airline": "AZG",
    "departure_time": "2026-06-17 12:17 UTC",
    "arrival_time": "2026-06-18 05:28 UTC",
    "duration_minutes": 1031,
    "duration_str": "17h 11m",
    "distance_km": 9234.5,
    "co2_kg": 159294.3
  },
  {
    "icao24": "448466",
    "callsign": "CHG855",
    "dep_airport_icao": "EBLG",
    "dep_airport_name": "Liege Airport",
    "dep_country": "BE",
    "dep_lat": 50.3811,
    "dep_lon": 5.2634,
    "arr_airport_icao": "VMMC",
    "arr_airport_name": "Macau International Airport",
    "arr_country": "MO",
    "arr_lat": 22.1496,
    "arr_lon": 113.592,
    "first_seen": 1781723191,
    "last_seen": 1781762175,
    "airline": "CHG",
    "departure_time": "2026-06-17 19:06 UTC",
    "arrival_time": "2026-06-18 05:56 UTC",
    "duration_minutes": 649,
    "duration_str": "10h 49m",
    "distance_km": 9339.3,
    "co2_kg": 161103.1
  },
  {
    "icao24": "452051",
    "callsign": "BCS12P",
    "dep_airport_icao": "EKCH",
    "dep_airport_name": "Copenhagen Kastrup Airport",
    "dep_country": "DK",
    "dep_lat": 55.6179,
    "dep_lon": 12.656,
    "arr_airport_icao": "ESMO",
    "arr_airport_name": "Oskarshamn Airport",
    "arr_country": "SE",
    "arr_lat": 57.3505,
    "arr_lon": 16.498,
    "first_seen": 1781756690,
    "last_seen": 1781758262,
    "airline": "BCS",
    "departure_time": "2026-06-18 04:24 UTC",
    "arrival_time": "2026-06-18 04:51 UTC",
    "duration_minutes": 26,
    "duration_str": "26m",
    "distance_km": 304.5,
    "co2_kg": 5252.4
  },
  {
    "icao24": "4601f9",
    "callsign": "FIN4J",
    "dep_airport_icao": "EFHK",
    "dep_airport_name": "Helsinki Vantaa Airport",
    "dep_country": "FI",
    "dep_lat": 60.3172,
    "dep_lon": 24.9633,
    "arr_airport_icao": "EFPH",
    "arr_airport_name": "Pyhoselka Airport",
    "arr_country": "FI",
    "arr_lat": 62.4647,
    "arr_lon": 30.0353,
    "first_seen": 1781754126,
    "last_seen": 1781757055,
    "airline": "Finnair",
    "departure_time": "2026-06-18 03:42 UTC",
    "arrival_time": "2026-06-18 04:30 UTC",
    "duration_minutes": 48,
    "duration_str": "48m",
    "distance_km": 360.3,
    "co2_kg": 6215.2
  },
  {
    "icao24": "4690e1",
    "callsign": "AEE352",
    "dep_airport_icao": "LGAV",
    "dep_airport_name": "Eleftherios Venizelos International Airport",
    "dep_country": "GR",
    "dep_lat": 37.9364,
    "dep_lon": 23.9445,
    "arr_airport_icao": "LGTL",
    "arr_airport_name": "Kasteli Airport",
    "arr_country": "GR",
    "arr_lat": 35.192,
    "arr_lon": 25.327,
    "first_seen": 1781757668,
    "last_seen": 1781758746,
    "airline": "AEE",
    "departure_time": "2026-06-18 04:41 UTC",
    "arrival_time": "2026-06-18 04:59 UTC",
    "duration_minutes": 17,
    "duration_str": "17m",
    "distance_km": 329.2,
    "co2_kg": 5678.4
  },
  {
    "icao24": "4692d1",
    "callsign": "AEE348",
    "dep_airport_icao": "LGAV",
    "dep_airport_name": "Eleftherios Venizelos International Airport",
    "dep_country": "GR",
    "dep_lat": 37.9364,
    "dep_lon": 23.9445,
    "arr_airport_icao": "LGTL",
    "arr_airport_name": "Kasteli Airport",
    "arr_country": "GR",
    "arr_lat": 35.192,
    "arr_lon": 25.327,
    "first_seen": 1781759514,
    "last_seen": 1781760657,
    "airline": "AEE",
    "departure_time": "2026-06-18 05:11 UTC",
    "arrival_time": "2026-06-18 05:30 UTC",
    "duration_minutes": 19,
    "duration_str": "19m",
    "distance_km": 329.2,
    "co2_kg": 5678.4
  },
  {
    "icao24": "46a5e7",
    "callsign": "SEH1JT",
    "dep_airport_icao": "LGAV",
    "dep_airport_name": "Eleftherios Venizelos International Airport",
    "dep_country": "GR",
    "dep_lat": 37.9364,
    "dep_lon": 23.9445,
    "arr_airport_icao": "LGKY",
    "arr_airport_name": "Kalymnos Airport",
    "arr_country": "GR",
    "arr_lat": 36.9633,
    "arr_lon": 26.9406,
    "first_seen": 1781756775,
    "last_seen": 1781757933,
    "airline": "SEH",
    "departure_time": "2026-06-18 04:26 UTC",
    "arrival_time": "2026-06-18 04:45 UTC",
    "duration_minutes": 19,
    "duration_str": "19m",
    "distance_km": 285.7,
    "co2_kg": 4929.1
  },
  {
    "icao24": "46d276",
    "callsign": "SEH1CF",
    "dep_airport_icao": "LGAV",
    "dep_airport_name": "Eleftherios Venizelos International Airport",
    "dep_country": "GR",
    "dep_lat": 37.9364,
    "dep_lon": 23.9445,
    "arr_airport_icao": "LGPZ",
    "arr_airport_name": "Aktion National Airport",
    "arr_country": "GR",
    "arr_lat": 38.9255,
    "arr_lon": 20.7653,
    "first_seen": 1781754765,
    "last_seen": 1781757430,
    "airline": "SEH",
    "departure_time": "2026-06-18 03:52 UTC",
    "arrival_time": "2026-06-18 04:37 UTC",
    "duration_minutes": 44,
    "duration_str": "44m",
    "distance_km": 297.9,
    "co2_kg": 5139.5
  },
  {
    "icao24": "471d61",
    "callsign": "WZZ912",
    "dep_airport_icao": "LZIB",
    "dep_airport_name": "M. R. Stefanik Airport",
    "dep_country": "SK",
    "dep_lat": 48.1702,
    "dep_lon": 17.2127,
    "arr_airport_icao": "LYBR",
    "arr_airport_name": "Berane Airport",
    "arr_country": "ME",
    "arr_lat": 42.839,
    "arr_lon": 19.862,
    "first_seen": 1781755655,
    "last_seen": 1781758567,
    "airline": "Wizz Air",
    "departure_time": "2026-06-18 04:07 UTC",
    "arrival_time": "2026-06-18 04:56 UTC",
    "duration_minutes": 48,
    "duration_str": "48m",
    "distance_km": 627.6,
    "co2_kg": 10826.5
  },
  {
    "icao24": "471f05",
    "callsign": "WZZ9445",
    "dep_airport_icao": "LCLK",
    "dep_airport_name": "Larnaca International Airport",
    "dep_country": "CY",
    "dep_lat": 34.8751,
    "dep_lon": 33.6249,
    "arr_airport_icao": "UDSG",
    "arr_airport_name": "Gyumri Shirak Airport",
    "arr_country": "AM",
    "arr_lat": 40.7504,
    "arr_lon": 43.8593,
    "first_seen": 1781753100,
    "last_seen": 1781758074,
    "airline": "Wizz Air",
    "departure_time": "2026-06-18 03:25 UTC",
    "arrival_time": "2026-06-18 04:47 UTC",
    "duration_minutes": 82,
    "duration_str": "1h 22m",
    "distance_km": 1110.1,
    "co2_kg": 19149.1
  },
  {
    "icao24": "478792",
    "callsign": "WIF7GT",
    "dep_airport_icao": "ENBO",
    "dep_airport_name": "Bod\u00f8 Airport",
    "dep_country": "NO",
    "dep_lat": 67.2692,
    "dep_lon": 14.3653,
    "arr_airport_icao": "ENSH",
    "arr_airport_name": "Svolv\u00e6r Helle Airport",
    "arr_country": "NO",
    "arr_lat": 68.2433,
    "arr_lon": 14.6692,
    "first_seen": 1781756184,
    "last_seen": 1781757275,
    "airline": "WIF",
    "departure_time": "2026-06-18 04:16 UTC",
    "arrival_time": "2026-06-18 04:34 UTC",
    "duration_minutes": 18,
    "duration_str": "18m",
    "distance_km": 109.1,
    "co2_kg": 1881.4
  },
  {
    "icao24": "47a2b4",
    "callsign": "LNPFF",
    "dep_airport_icao": "ENKJ",
    "dep_airport_name": "Kjeller Airport",
    "dep_country": "NO",
    "dep_lat": 59.9693,
    "dep_lon": 11.0361,
    "arr_airport_icao": "ENKJ",
    "arr_airport_name": "Kjeller Airport",
    "arr_country": "NO",
    "arr_lat": 59.9693,
    "arr_lon": 11.0361,
    "first_seen": 1781762403,
    "last_seen": 1781763284,
    "airline": "LNP",
    "departure_time": "2026-06-18 06:00 UTC",
    "arrival_time": "2026-06-18 06:14 UTC",
    "duration_minutes": 14,
    "duration_str": "14m",
    "distance_km": 0.0,
    "co2_kg": 0.0
  },
  {
    "icao24": "48c230",
    "callsign": "RYS5089",
    "dep_airport_icao": "EPKT",
    "dep_airport_name": "Katowice International Airport",
    "dep_country": "PL",
    "dep_lat": 50.4743,
    "dep_lon": 19.08,
    "arr_airport_icao": "LYPO",
    "arr_airport_name": "Cemovsko Polje Airport",
    "arr_country": "ME",
    "arr_lat": 42.42232,
    "arr_lon": 19.29078,
    "first_seen": 1781752887,
    "last_seen": 1781756668,
    "airline": "RYS",
    "departure_time": "2026-06-18 03:21 UTC",
    "arrival_time": "2026-06-18 04:24 UTC",
    "duration_minutes": 63,
    "duration_str": "1h 3m",
    "distance_km": 895.5,
    "co2_kg": 15447.1
  },
  {
    "icao24": "49d108",
    "callsign": "OKRDS",
    "dep_airport_icao": "LZIB",
    "dep_airport_name": "M. R. Stefanik Airport",
    "dep_country": "SK",
    "dep_lat": 48.1702,
    "dep_lon": 17.2127,
    "arr_airport_icao": "LOAS",
    "arr_airport_name": "Spitzerberg Airport",
    "arr_country": "AT",
    "arr_lat": 48.1022,
    "arr_lon": 16.9353,
    "first_seen": 1781757910,
    "last_seen": 1781758487,
    "airline": "OKR",
    "departure_time": "2026-06-18 04:45 UTC",
    "arrival_time": "2026-06-18 04:54 UTC",
    "duration_minutes": 9,
    "duration_str": "9m",
    "distance_km": 21.9,
    "co2_kg": 378.3
  },
  {
    "icao24": "49d2d6",
    "callsign": "VAA010",
    "dep_airport_icao": "UGMM",
    "dep_airport_name": "Mukhrani Airport",
    "dep_country": "GE",
    "dep_lat": 41.916,
    "dep_lon": 44.566,
    "arr_airport_icao": "UGMS",
    "arr_airport_name": "UGMS",
    "arr_country": "",
    "arr_lat": null,
    "arr_lon": null,
    "first_seen": 1781758919,
    "last_seen": 1781760938,
    "airline": "VAA",
    "departure_time": "2026-06-18 05:01 UTC",
    "arrival_time": "2026-06-18 05:35 UTC",
    "duration_minutes": 33,
    "duration_str": "33m",
    "distance_km": 0.0,
    "co2_kg": 0.0
  },
  {
    "icao24": "49d418",
    "callsign": "TVS5QT",
    "dep_airport_icao": "LKPR",
    "dep_airport_name": "V\u00e1clav Havel Airport",
    "dep_country": "CZ",
    "dep_lat": 50.1008,
    "dep_lon": 14.26,
    "arr_airport_icao": "LAVL",
    "arr_airport_name": "Vlora Internationa Airport",
    "arr_country": "AL",
    "arr_lat": 40.605556,
    "arr_lon": 19.426111,
    "first_seen": 1781752817,
    "last_seen": 1781758040,
    "airline": "TVS",
    "departure_time": "2026-06-18 03:20 UTC",
    "arrival_time": "2026-06-18 04:47 UTC",
    "duration_minutes": 87,
    "duration_str": "1h 27m",
    "distance_km": 1129.7,
    "co2_kg": 19486.7
  },
  {
    "icao24": "4ac92a",
    "callsign": "JON07",
    "dep_airport_icao": "ESNZ",
    "dep_airport_name": "Ostersund Airport",
    "dep_country": "SE",
    "dep_lat": 63.1944,
    "dep_lon": 14.5003,
    "arr_airport_icao": "ESNX",
    "arr_airport_name": "Arvidsjaur Airport",
    "arr_country": "SE",
    "arr_lat": 65.5903,
    "arr_lon": 19.2819,
    "first_seen": 1781760701,
    "last_seen": 1781762145,
    "airline": "JON",
    "departure_time": "2026-06-18 05:31 UTC",
    "arrival_time": "2026-06-18 05:55 UTC",
    "duration_minutes": 24,
    "duration_str": "24m",
    "distance_km": 351.6,
    "co2_kg": 6065.8
  },
  {
    "icao24": "4baa87",
    "callsign": "THY2HR",
    "dep_airport_icao": "LTFM",
    "dep_airport_name": "Istanbul Airport",
    "dep_country": "TR",
    "dep_lat": 41.27533,
    "dep_lon": 28.752,
    "arr_airport_icao": "LTBJ",
    "arr_airport_name": "Adnan Menderes International Airport",
    "arr_country": "TR",
    "arr_lat": 38.2924,
    "arr_lon": 27.157,
    "first_seen": 1781757101,
    "last_seen": 1781759376,
    "airline": "Turkish Airlines",
    "departure_time": "2026-06-18 04:31 UTC",
    "arrival_time": "2026-06-18 05:09 UTC",
    "duration_minutes": 37,
    "duration_str": "37m",
    "distance_km": 358.6,
    "co2_kg": 6185.5
  },
  {
    "icao24": "4c01e5",
    "callsign": "ASL84H",
    "dep_airport_icao": "LYBE",
    "dep_airport_name": "Belgrade Nikola Tesla Airport",
    "dep_country": "RS",
    "dep_lat": 44.8184,
    "dep_lon": 20.3091,
    "arr_airport_icao": "LYVA",
    "arr_airport_name": "Divci Airport",
    "arr_country": "RS",
    "arr_lat": 44.29782,
    "arr_lon": 20.02191,
    "first_seen": 1781758549,
    "last_seen": 1781759801,
    "airline": "ASL",
    "departure_time": "2026-06-18 04:55 UTC",
    "arrival_time": "2026-06-18 05:16 UTC",
    "duration_minutes": 20,
    "duration_str": "20m",
    "distance_km": 62.2,
    "co2_kg": 1072.9
  },
  {
    "icao24": "4ca621",
    "callsign": "RYR6FR",
    "dep_airport_icao": "LICJ",
    "dep_airport_name": "Palermo / Punta Raisi Airport",
    "dep_country": "IT",
    "dep_lat": 38.176,
    "dep_lon": 13.091,
    "arr_airport_icao": "LIRN",
    "arr_airport_name": "Napoli / Capodichino International Airport",
    "arr_country": "IT",
    "arr_lat": 40.886,
    "arr_lon": 14.2908,
    "first_seen": 1781758340,
    "last_seen": 1781759741,
    "airline": "Ryanair",
    "departure_time": "2026-06-18 04:52 UTC",
    "arrival_time": "2026-06-18 05:15 UTC",
    "duration_minutes": 23,
    "duration_str": "23m",
    "distance_km": 318.4,
    "co2_kg": 5492.6
  },
  {
    "icao24": "4cafb4",
    "callsign": "RYR95YC",
    "dep_airport_icao": "EDJA",
    "dep_airport_name": "Memmingen Allgau Airport",
    "dep_country": "DE",
    "dep_lat": 47.9888,
    "dep_lon": 10.2395,
    "arr_airport_icao": "LIAU",
    "arr_airport_name": "Capua Airport",
    "arr_country": "IT",
    "arr_lat": 41.116,
    "arr_lon": 14.178,
    "first_seen": 1781755643,
    "last_seen": 1781759306,
    "airline": "Ryanair",
    "departure_time": "2026-06-18 04:07 UTC",
    "arrival_time": "2026-06-18 05:08 UTC",
    "duration_minutes": 61,
    "duration_str": "1h 1m",
    "distance_km": 825.2,
    "co2_kg": 14234.7
  },
  {
    "icao24": "4d2257",
    "callsign": "RYR8XV",
    "dep_airport_icao": "LIME",
    "dep_airport_name": "Bergamo / Orio Al Serio Airport",
    "dep_country": "IT",
    "dep_lat": 45.6739,
    "dep_lon": 9.70417,
    "arr_airport_icao": "LYTV",
    "arr_airport_name": "Tivat Airport",
    "arr_country": "ME",
    "arr_lat": 42.4047,
    "arr_lon": 18.7233,
    "first_seen": 1781755688,
    "last_seen": 1781759341,
    "airline": "Ryanair",
    "departure_time": "2026-06-18 04:08 UTC",
    "arrival_time": "2026-06-18 05:09 UTC",
    "duration_minutes": 60,
    "duration_str": "1h 0m",
    "distance_km": 806.7,
    "co2_kg": 13916.3
  },
  {
    "icao24": "4d227d",
    "callsign": "RYR3VU",
    "dep_airport_icao": "LEZL",
    "dep_airport_name": "Sevilla Airport",
    "dep_country": "ES",
    "dep_lat": 37.418,
    "dep_lon": -5.89311,
    "arr_airport_icao": "LELM",
    "arr_airport_name": "Almansa Airport",
    "arr_country": "ES",
    "arr_lat": 38.895,
    "arr_lon": -1.11318,
    "first_seen": 1781757563,
    "last_seen": 1781759930,
    "airline": "Ryanair",
    "departure_time": "2026-06-18 04:39 UTC",
    "arrival_time": "2026-06-18 05:18 UTC",
    "duration_minutes": 39,
    "duration_str": "39m",
    "distance_km": 449.0,
    "co2_kg": 7744.8
  },
  {
    "icao24": "4d22bf",
    "callsign": "RYR2GN",
    "dep_airport_icao": "LOWW",
    "dep_airport_name": "Vienna International Airport",
    "dep_country": "AT",
    "dep_lat": 48.1103,
    "dep_lon": 16.5697,
    "arr_airport_icao": "LYPO",
    "arr_airport_name": "Cemovsko Polje Airport",
    "arr_country": "ME",
    "arr_lat": 42.42232,
    "arr_lon": 19.29078,
    "first_seen": 1781756019,
    "last_seen": 1781759016,
    "airline": "Ryanair",
    "departure_time": "2026-06-18 04:13 UTC",
    "arrival_time": "2026-06-18 05:03 UTC",
    "duration_minutes": 49,
    "duration_str": "49m",
    "distance_km": 667.2,
    "co2_kg": 11510.0
  },
  {
    "icao24": "4d239a",
    "callsign": "SEJ622",
    "dep_airport_icao": "VIDP",
    "dep_airport_name": "Indira Gandhi International Airport",
    "dep_country": "IN",
    "dep_lat": 28.5665,
    "dep_lon": 77.1031,
    "arr_airport_icao": "VNSB",
    "arr_airport_name": "VNSB",
    "arr_country": "",
    "arr_lat": null,
    "arr_lon": null,
    "first_seen": 1781751433,
    "last_seen": 1781756515,
    "airline": "SEJ",
    "departure_time": "2026-06-18 02:57 UTC",
    "arrival_time": "2026-06-18 04:21 UTC",
    "duration_minutes": 84,
    "duration_str": "1h 24m",
    "distance_km": 0.0,
    "co2_kg": 0.0
  },
  {
    "icao24": "501c4b",
    "callsign": "CTN6B",
    "dep_airport_icao": "LDDU",
    "dep_airport_name": "Dubrovnik Airport",
    "dep_country": "HR",
    "dep_lat": 42.5614,
    "dep_lon": 18.2682,
    "arr_airport_icao": "LDRO",
    "arr_airport_name": "Otocac Airport",
    "arr_country": "HR",
    "arr_lat": 44.84777,
    "arr_lon": 15.28662,
    "first_seen": 1781756869,
    "last_seen": 1781758959,
    "airline": "CTN",
    "departure_time": "2026-06-18 04:27 UTC",
    "arrival_time": "2026-06-18 05:02 UTC",
    "duration_minutes": 34,
    "duration_str": "34m",
    "distance_km": 349.3,
    "co2_kg": 6026.2
  },
  {
    "icao24": "7020a2",
    "callsign": "UBG143",
    "dep_airport_icao": "VGZR",
    "dep_airport_name": "VGZR",
    "dep_country": "",
    "dep_lat": null,
    "dep_lon": null,
    "arr_airport_icao": "VGEG",
    "arr_airport_name": "Shah Amanat International Airport",
    "arr_country": "BD",
    "arr_lat": 22.2496,
    "arr_lon": 91.8133,
    "first_seen": 1781755475,
    "last_seen": 1781757568,
    "airline": "UBG",
    "departure_time": "2026-06-18 04:04 UTC",
    "arrival_time": "2026-06-18 04:39 UTC",
    "duration_minutes": 34,
    "duration_str": "34m",
    "distance_km": 0.0,
    "co2_kg": 0.0
  },
  {
    "icao24": "7020b4",
    "callsign": "UBG217",
    "dep_airport_icao": "VGZR",
    "dep_airport_name": "VGZR",
    "dep_country": "",
    "dep_lat": null,
    "dep_lon": null,
    "arr_airport_icao": "VYEL",
    "arr_airport_name": "Naypyidaw Airport",
    "arr_country": "MM",
    "arr_lat": 19.6235,
    "arr_lon": 96.201,
    "first_seen": 1781755936,
    "last_seen": 1781760086,
    "airline": "UBG",
    "departure_time": "2026-06-18 04:12 UTC",
    "arrival_time": "2026-06-18 05:21 UTC",
    "duration_minutes": 69,
    "duration_str": "1h 9m",
    "distance_km": 0.0,
    "co2_kg": 0.0
  },
  {
    "icao24": "717cc9",
    "callsign": "HZAL65",
    "dep_airport_icao": "OEAA",
    "dep_airport_name": "Abu Ali Airport",
    "dep_country": "SA",
    "dep_lat": 27.3191,
    "dep_lon": 49.5871,
    "arr_airport_icao": "OEAA",
    "arr_airport_name": "Abu Ali Airport",
    "arr_country": "SA",
    "arr_lat": 27.3191,
    "arr_lon": 49.5871,
    "first_seen": 1781757925,
    "last_seen": 1781758038,
    "airline": "HZA",
    "departure_time": "2026-06-18 04:45 UTC",
    "arrival_time": "2026-06-18 04:47 UTC",
    "duration_minutes": 1,
    "duration_str": "1m",
    "distance_km": 0.0,
    "co2_kg": 0.0
  },
  {
    "icao24": "71c302",
    "callsign": "JJA1453",
    "dep_airport_icao": "RKPK",
    "dep_airport_name": "Gimhae International Airport",
    "dep_country": "KR",
    "dep_lat": 35.1795,
    "dep_lon": 128.938,
    "arr_airport_icao": "RJDB",
    "arr_airport_name": "Iki Airport",
    "arr_country": "JP",
    "arr_lat": 33.749,
    "arr_lon": 129.785,
    "first_seen": 1781756171,
    "last_seen": 1781757242,
    "airline": "JJA",
    "departure_time": "2026-06-18 04:16 UTC",
    "arrival_time": "2026-06-18 04:34 UTC",
    "duration_minutes": 17,
    "duration_str": "17m",
    "distance_km": 177.0,
    "co2_kg": 3053.3
  },
  {
    "icao24": "71f091",
    "callsign": "IY31",
    "dep_airport_icao": "RKSM",
    "dep_airport_name": "Seoul Air Base",
    "dep_country": "KR",
    "dep_lat": 37.4458,
    "dep_lon": 127.114,
    "arr_airport_icao": "RK48",
    "arr_airport_name": "G 419 Airport",
    "arr_country": "KR",
    "arr_lat": 37.7032,
    "arr_lon": 127.905,
    "first_seen": 1781755625,
    "last_seen": 1781756768,
    "airline": "",
    "departure_time": "2026-06-18 04:07 UTC",
    "arrival_time": "2026-06-18 04:26 UTC",
    "duration_minutes": 19,
    "duration_str": "19m",
    "distance_km": 75.4,
    "co2_kg": 1299.9
  },
  {
    "icao24": "71f2cc",
    "callsign": "CU31",
    "dep_airport_icao": "RKPK",
    "dep_airport_name": "Gimhae International Airport",
    "dep_country": "KR",
    "dep_lat": 35.1795,
    "dep_lon": 128.938,
    "arr_airport_icao": "RK6D",
    "arr_airport_name": "G 710 Airport",
    "arr_country": "KR",
    "arr_lat": 35.3421,
    "arr_lon": 127.03,
    "first_seen": 1781756809,
    "last_seen": 1781758705,
    "airline": "",
    "departure_time": "2026-06-18 04:26 UTC",
    "arrival_time": "2026-06-18 04:58 UTC",
    "duration_minutes": 31,
    "duration_str": "31m",
    "distance_km": 174.2,
    "co2_kg": 3004.5
  },
  {
    "icao24": "738286",
    "callsign": "ISR041",
    "dep_airport_icao": "LLBG",
    "dep_airport_name": "Ben Gurion International Airport",
    "dep_country": "IL",
    "dep_lat": 32.0114,
    "dep_lon": 34.8867,
    "arr_airport_icao": "LLMR",
    "arr_airport_name": "Mitzpe Ramon Airfield",
    "arr_country": "IL",
    "arr_lat": 30.6506,
    "arr_lon": 34.8069,
    "first_seen": 1781758540,
    "last_seen": 1781759833,
    "airline": "ISR",
    "departure_time": "2026-06-18 04:55 UTC",
    "arrival_time": "2026-06-18 05:17 UTC",
    "duration_minutes": 21,
    "duration_str": "21m",
    "distance_km": 151.5,
    "co2_kg": 2613.4
  },
  {
    "icao24": "738485",
    "callsign": "AIZ801",
    "dep_airport_icao": "LLBG",
    "dep_airport_name": "Ben Gurion International Airport",
    "dep_country": "IL",
    "dep_lat": 32.0114,
    "dep_lon": 34.8867,
    "arr_airport_icao": "LLMR",
    "arr_airport_name": "Mitzpe Ramon Airfield",
    "arr_country": "IL",
    "arr_lat": 30.6506,
    "arr_lon": 34.8069,
    "first_seen": 1781755414,
    "last_seen": 1781756676,
    "airline": "AIZ",
    "departure_time": "2026-06-18 04:03 UTC",
    "arrival_time": "2026-06-18 04:24 UTC",
    "duration_minutes": 21,
    "duration_str": "21m",
    "distance_km": 151.5,
    "co2_kg": 2613.4
  },
  {
    "icao24": "73934e",
    "callsign": "HEZ351",
    "dep_airport_icao": "LLBG",
    "dep_airport_name": "Ben Gurion International Airport",
    "dep_country": "IL",
    "dep_lat": 32.0114,
    "dep_lon": 34.8867,
    "arr_airport_icao": "LAKV",
    "arr_airport_name": "Kucove Air Base",
    "arr_country": "AL",
    "arr_lat": 40.7719,
    "arr_lon": 19.9019,
    "first_seen": 1781749166,
    "last_seen": 1781757516,
    "airline": "HEZ",
    "departure_time": "2026-06-18 02:19 UTC",
    "arrival_time": "2026-06-18 04:38 UTC",
    "duration_minutes": 139,
    "duration_str": "2h 19m",
    "distance_km": 1653.8,
    "co2_kg": 28528.3
  },
  {
    "icao24": "744824",
    "callsign": "RJA435",
    "dep_airport_icao": "OJAI",
    "dep_airport_name": "Queen Alia International Airport",
    "dep_country": "JO",
    "dep_lat": 31.7226,
    "dep_lon": 35.9932,
    "arr_airport_icao": "OS69",
    "arr_airport_name": "OS69",
    "arr_country": "",
    "arr_lat": null,
    "arr_lon": null,
    "first_seen": 1781755537,
    "last_seen": 1781756704,
    "airline": "Royal Jordanian",
    "departure_time": "2026-06-18 04:05 UTC",
    "arrival_time": "2026-06-18 04:25 UTC",
    "duration_minutes": 19,
    "duration_str": "19m",
    "distance_km": 0.0,
    "co2_kg": 0.0
  },
  {
    "icao24": "758081",
    "callsign": "GAP2037",
    "dep_airport_icao": "RPLL",
    "dep_airport_name": "Ninoy Aquino International Airport",
    "dep_country": "PH",
    "dep_lat": 14.5086,
    "dep_lon": 121.02,
    "arr_airport_icao": "RPVL",
    "arr_airport_name": "Wasig Airport",
    "arr_country": "PH",
    "arr_lat": 12.5361,
    "arr_lon": 121.481,
    "first_seen": 1781755837,
    "last_seen": 1781757300,
    "airline": "GAP",
    "departure_time": "2026-06-18 04:10 UTC",
    "arrival_time": "2026-06-18 04:35 UTC",
    "duration_minutes": 24,
    "duration_str": "24m",
    "distance_km": 224.9,
    "co2_kg": 3879.9
  },
  {
    "icao24": "758560",
    "callsign": "APG225",
    "dep_airport_icao": "RPLL",
    "dep_airport_name": "Ninoy Aquino International Airport",
    "dep_country": "PH",
    "dep_lat": 14.5086,
    "dep_lon": 121.02,
    "arr_airport_icao": "RPVL",
    "arr_airport_name": "Wasig Airport",
    "arr_country": "PH",
    "arr_lat": 12.5361,
    "arr_lon": 121.481,
    "first_seen": 1781756459,
    "last_seen": 1781757999,
    "airline": "APG",
    "departure_time": "2026-06-18 04:20 UTC",
    "arrival_time": "2026-06-18 04:46 UTC",
    "duration_minutes": 25,
    "duration_str": "25m",
    "distance_km": 224.9,
    "co2_kg": 3879.9
  },
  {
    "icao24": "758827",
    "callsign": "CEB903",
    "dep_airport_icao": "RPLL",
    "dep_airport_name": "Ninoy Aquino International Airport",
    "dep_country": "PH",
    "dep_lat": 14.5086,
    "dep_lon": 121.02,
    "arr_airport_icao": "RPVL",
    "arr_airport_name": "Wasig Airport",
    "arr_country": "PH",
    "arr_lat": 12.5361,
    "arr_lon": 121.481,
    "first_seen": 1781756111,
    "last_seen": 1781757569,
    "airline": "CEB",
    "departure_time": "2026-06-18 04:15 UTC",
    "arrival_time": "2026-06-18 04:39 UTC",
    "duration_minutes": 24,
    "duration_str": "24m",
    "distance_km": 224.9,
    "co2_kg": 3879.9
  },
  {
    "icao24": "7801b0",
    "callsign": "CPA740",
    "dep_airport_icao": "VVNB",
    "dep_airport_name": "Noi Bai International Airport",
    "dep_country": "VN",
    "dep_lat": 21.2212,
    "dep_lon": 105.807,
    "arr_airport_icao": "VMMC",
    "arr_airport_name": "Macau International Airport",
    "arr_country": "MO",
    "arr_lat": 22.1496,
    "arr_lon": 113.592,
    "first_seen": 1781756628,
    "last_seen": 1781760848,
    "airline": "Cathay Pacific",
    "departure_time": "2026-06-18 04:23 UTC",
    "arrival_time": "2026-06-18 05:34 UTC",
    "duration_minutes": 70,
    "duration_str": "1h 10m",
    "distance_km": 810.9,
    "co2_kg": 13987.8
  },
  {
    "icao24": "780a89",
    "callsign": "CPA250",
    "dep_airport_icao": "EGLL",
    "dep_airport_name": "London Heathrow Airport",
    "dep_country": "GB",
    "dep_lat": 51.4706,
    "dep_lon": -0.46194,
    "arr_airport_icao": "VMMC",
    "arr_airport_name": "Macau International Airport",
    "arr_country": "MO",
    "arr_lat": 22.1496,
    "arr_lon": 113.592,
    "first_seen": 1781718415,
    "last_seen": 1781760131,
    "airline": "Cathay Pacific",
    "departure_time": "2026-06-17 17:46 UTC",
    "arrival_time": "2026-06-18 05:22 UTC",
    "duration_minutes": 695,
    "duration_str": "11h 35m",
    "distance_km": 9626.4,
    "co2_kg": 166056.2
  },
  {
    "icao24": "780aa1",
    "callsign": "HKE541",
    "dep_airport_icao": "VVNS",
    "dep_airport_name": "Na-San Airport",
    "dep_country": "VN",
    "dep_lat": 21.217,
    "dep_lon": 104.033,
    "arr_airport_icao": "ZGSD",
    "arr_airport_name": "Zhuhai Airport",
    "arr_country": "CN",
    "arr_lat": 22.0064,
    "arr_lon": 113.376,
    "first_seen": 1781752230,
    "last_seen": 1781756732,
    "airline": "HKE",
    "departure_time": "2026-06-18 03:10 UTC",
    "arrival_time": "2026-06-18 04:25 UTC",
    "duration_minutes": 75,
    "duration_str": "1h 15m",
    "distance_km": 969.7,
    "co2_kg": 16727.1
  },
  {
    "icao24": "789216",
    "callsign": "CPA821",
    "dep_airport_icao": "CYYZ",
    "dep_airport_name": "Toronto Pearson International Airport",
    "dep_country": "CA",
    "dep_lat": 43.6772,
    "dep_lon": -79.6306,
    "arr_airport_icao": "ZGSD",
    "arr_airport_name": "Zhuhai Airport",
    "arr_country": "CN",
    "arr_lat": 22.0064,
    "arr_lon": 113.376,
    "first_seen": 1781707165,
    "last_seen": 1781757481,
    "airline": "Cathay Pacific",
    "departure_time": "2026-06-17 14:39 UTC",
    "arrival_time": "2026-06-18 04:38 UTC",
    "duration_minutes": 838,
    "duration_str": "13h 58m",
    "distance_km": 12591.6,
    "co2_kg": 217205.7
  },
  {
    "icao24": "7c01b5",
    "callsign": "AMF",
    "dep_airport_icao": "YPJT",
    "dep_airport_name": "Perth Jandakot Airport",
    "dep_country": "AU",
    "dep_lat": -32.0975,
    "dep_lon": 115.881,
    "arr_airport_icao": "YMRW",
    "arr_airport_name": "Morawa Airport",
    "arr_country": "AU",
    "arr_lat": -29.2017,
    "arr_lon": 116.022,
    "first_seen": 1781757585,
    "last_seen": 1781760403,
    "airline": "AMF",
    "departure_time": "2026-06-18 04:39 UTC",
    "arrival_time": "2026-06-18 05:26 UTC",
    "duration_minutes": 46,
    "duration_str": "46m",
    "distance_km": 322.3,
    "co2_kg": 5559.3
  },
  {
    "icao24": "7c01c1",
    "callsign": "AM280",
    "dep_airport_icao": "YSSY",
    "dep_airport_name": "Sydney Kingsford Smith International Airport",
    "dep_country": "AU",
    "dep_lat": -33.9461,
    "dep_lon": 151.177,
    "arr_airport_icao": "YCUA",
    "arr_airport_name": "Cudal Airport",
    "arr_country": "AU",
    "arr_lat": -33.2783,
    "arr_lon": 148.763,
    "first_seen": 1781759068,
    "last_seen": 1781761204,
    "airline": "",
    "departure_time": "2026-06-18 05:04 UTC",
    "arrival_time": "2026-06-18 05:40 UTC",
    "duration_minutes": 35,
    "duration_str": "35m",
    "distance_km": 235.5,
    "co2_kg": 4063.2
  },
  {
    "icao24": "7c045f",
    "callsign": "JST223",
    "dep_airport_icao": "YSSY",
    "dep_airport_name": "Sydney Kingsford Smith International Airport",
    "dep_country": "AU",
    "dep_lat": -33.9461,
    "dep_lon": 151.177,
    "arr_airport_icao": "NZQN",
    "arr_airport_name": "Queenstown International Airport",
    "arr_country": "NZ",
    "arr_lat": -45.0211,
    "arr_lon": 168.739,
    "first_seen": 1781751485,
    "last_seen": 1781759628,
    "airline": "JST",
    "departure_time": "2026-06-18 02:58 UTC",
    "arrival_time": "2026-06-18 05:13 UTC",
    "duration_minutes": 135,
    "duration_str": "2h 15m",
    "distance_km": 1938.9,
    "co2_kg": 33446.4
  },
  {
    "icao24": "7c1c45",
    "callsign": "FD527",
    "dep_airport_icao": "YPLC",
    "dep_airport_name": "Port Lincoln Airport",
    "dep_country": "AU",
    "dep_lat": -34.6053,
    "dep_lon": 135.88,
    "arr_airport_icao": "YCUS",
    "arr_airport_name": "Cummins Airport",
    "arr_country": "AU",
    "arr_lat": -34.2083,
    "arr_lon": 135.642,
    "first_seen": 1781757127,
    "last_seen": 1781757873,
    "airline": "",
    "departure_time": "2026-06-18 04:32 UTC",
    "arrival_time": "2026-06-18 04:44 UTC",
    "duration_minutes": 12,
    "duration_str": "12m",
    "distance_km": 49.2,
    "co2_kg": 849.5
  },
  {
    "icao24": "7c1c49",
    "callsign": "FD528",
    "dep_airport_icao": "YPAD",
    "dep_airport_name": "Adelaide International Airport",
    "dep_country": "AU",
    "dep_lat": -34.945,
    "dep_lon": 138.53101,
    "arr_airport_icao": "YWKI",
    "arr_airport_name": "Waikerie Airport",
    "arr_country": "AU",
    "arr_lat": -34.1839,
    "arr_lon": 140.03101,
    "first_seen": 1781756920,
    "last_seen": 1781758189,
    "airline": "",
    "departure_time": "2026-06-18 04:28 UTC",
    "arrival_time": "2026-06-18 04:49 UTC",
    "duration_minutes": 21,
    "duration_str": "21m",
    "distance_km": 161.3,
    "co2_kg": 2782.9
  },
  {
    "icao24": "7c3ad2",
    "callsign": "LWK",
    "dep_airport_icao": "YPJT",
    "dep_airport_name": "Perth Jandakot Airport",
    "dep_country": "AU",
    "dep_lat": -32.0975,
    "dep_lon": 115.881,
    "arr_airport_icao": "YGUL",
    "arr_airport_name": "Gullewa Airport",
    "arr_country": "AU",
    "arr_lat": -28.6333,
    "arr_lon": 116.283,
    "first_seen": 1781754663,
    "last_seen": 1781758066,
    "airline": "LWK",
    "departure_time": "2026-06-18 03:51 UTC",
    "arrival_time": "2026-06-18 04:47 UTC",
    "duration_minutes": 56,
    "duration_str": "56m",
    "distance_km": 387.1,
    "co2_kg": 6677.9
  },
  {
    "icao24": "7c3ad6",
    "callsign": "FD629",
    "dep_airport_icao": "YPJT",
    "dep_airport_name": "Perth Jandakot Airport",
    "dep_country": "AU",
    "dep_lat": -32.0975,
    "dep_lon": 115.881,
    "arr_airport_icao": "YDRA",
    "arr_airport_name": "Dongara Airport",
    "arr_country": "AU",
    "arr_lat": -29.3,
    "arr_lon": 114.933,
    "first_seen": 1781756207,
    "last_seen": 1781758573,
    "airline": "",
    "departure_time": "2026-06-18 04:16 UTC",
    "arrival_time": "2026-06-18 04:56 UTC",
    "duration_minutes": 39,
    "duration_str": "39m",
    "distance_km": 324.0,
    "co2_kg": 5589.0
  },
  {
    "icao24": "7c6ae2",
    "callsign": "LR455",
    "dep_airport_icao": "YBBN",
    "dep_airport_name": "Brisbane International Airport",
    "dep_country": "AU",
    "dep_lat": -27.3842,
    "dep_lon": 153.117,
    "arr_airport_icao": "YPAC",
    "arr_airport_name": "Pacific Haven Airport",
    "arr_country": "AU",
    "arr_lat": -25.2367,
    "arr_lon": 152.543,
    "first_seen": 1781756652,
    "last_seen": 1781758648,
    "airline": "",
    "departure_time": "2026-06-18 04:24 UTC",
    "arrival_time": "2026-06-18 04:57 UTC",
    "duration_minutes": 33,
    "duration_str": "33m",
    "distance_km": 245.5,
    "co2_kg": 4235.7
  },
  {
    "icao24": "7c6b41",
    "callsign": "JST705",
    "dep_airport_icao": "YMML",
    "dep_airport_name": "Melbourne International Airport",
    "dep_country": "AU",
    "dep_lat": -37.6733,
    "dep_lon": 144.843,
    "arr_airport_icao": "YLHL",
    "arr_airport_name": "Long Hill Airport",
    "arr_country": "AU",
    "arr_lat": -41.3333,
    "arr_lon": 146.5,
    "first_seen": 1781754552,
    "last_seen": 1781756678,
    "airline": "JST",
    "departure_time": "2026-06-18 03:49 UTC",
    "arrival_time": "2026-06-18 04:24 UTC",
    "duration_minutes": 35,
    "duration_str": "35m",
    "distance_km": 431.1,
    "co2_kg": 7435.9
  },
  {
    "icao24": "7c7891",
    "callsign": "JST293",
    "dep_airport_icao": "NZAA",
    "dep_airport_name": "Auckland International Airport",
    "dep_country": "NZ",
    "dep_lat": -37.0081,
    "dep_lon": 174.79201,
    "arr_airport_icao": "NZOA",
    "arr_airport_name": "Omarama Glider Airport",
    "arr_country": "NZ",
    "arr_lat": -44.4867,
    "arr_lon": 169.98599,
    "first_seen": 1781752142,
    "last_seen": 1781756872,
    "airline": "JST",
    "departure_time": "2026-06-18 03:09 UTC",
    "arrival_time": "2026-06-18 04:27 UTC",
    "duration_minutes": 78,
    "duration_str": "1h 18m",
    "distance_km": 924.5,
    "co2_kg": 15947.2
  },
  {
    "icao24": "7c78ab",
    "callsign": "QLK1535",
    "dep_airport_icao": "YSSY",
    "dep_airport_name": "Sydney Kingsford Smith International Airport",
    "dep_country": "AU",
    "dep_lat": -33.9461,
    "dep_lon": 151.177,
    "arr_airport_icao": "YFLI",
    "arr_airport_name": "Flinders Island Airport",
    "arr_country": "AU",
    "arr_lat": -40.0917,
    "arr_lon": 147.993,
    "first_seen": 1781754116,
    "last_seen": 1781757864,
    "airline": "QLK",
    "departure_time": "2026-06-18 03:41 UTC",
    "arrival_time": "2026-06-18 04:44 UTC",
    "duration_minutes": 62,
    "duration_str": "1h 2m",
    "distance_km": 739.4,
    "co2_kg": 12754.2
  },
  {
    "icao24": "7c79d7",
    "callsign": "HARR85",
    "dep_airport_icao": "YPJT",
    "dep_airport_name": "Perth Jandakot Airport",
    "dep_country": "AU",
    "dep_lat": -32.0975,
    "dep_lon": 115.881,
    "arr_airport_icao": "YPJT",
    "arr_airport_name": "Perth Jandakot Airport",
    "arr_country": "AU",
    "arr_lat": -32.0975,
    "arr_lon": 115.881,
    "first_seen": 1781757950,
    "last_seen": 1781761353,
    "airline": "HAR",
    "departure_time": "2026-06-18 04:45 UTC",
    "arrival_time": "2026-06-18 05:42 UTC",
    "duration_minutes": 56,
    "duration_str": "56m",
    "distance_km": 0.0,
    "co2_kg": 0.0
  },
  {
    "icao24": "7c7a4a",
    "callsign": "VOZ1117",
    "dep_airport_icao": "YBBN",
    "dep_airport_name": "Brisbane International Airport",
    "dep_country": "AU",
    "dep_lat": -27.3842,
    "dep_lon": 153.117,
    "arr_airport_icao": "YLAK",
    "arr_airport_name": "Lakeside Airpark",
    "arr_country": "AU",
    "arr_lat": -20.6817,
    "arr_lon": 148.62801,
    "first_seen": 1781752312,
    "last_seen": 1781756764,
    "airline": "Virgin Australia",
    "departure_time": "2026-06-18 03:11 UTC",
    "arrival_time": "2026-06-18 04:26 UTC",
    "duration_minutes": 74,
    "duration_str": "1h 14m",
    "distance_km": 873.4,
    "co2_kg": 15066.7
  },
  {
    "icao24": "7c7aab",
    "callsign": "VOZ1090",
    "dep_airport_icao": "YSSY",
    "dep_airport_name": "Sydney Kingsford Smith International Airport",
    "dep_country": "AU",
    "dep_lat": -33.9461,
    "dep_lon": 151.177,
    "arr_airport_icao": "YFLI",
    "arr_airport_name": "Flinders Island Airport",
    "arr_country": "AU",
    "arr_lat": -40.0917,
    "arr_lon": 147.993,
    "first_seen": 1781754777,
    "last_seen": 1781758216,
    "airline": "Virgin Australia",
    "departure_time": "2026-06-18 03:52 UTC",
    "arrival_time": "2026-06-18 04:50 UTC",
    "duration_minutes": 57,
    "duration_str": "57m",
    "distance_km": 739.4,
    "co2_kg": 12754.2
  },
  {
    "icao24": "7c802a",
    "callsign": "RXA5732",
    "dep_airport_icao": "YBBN",
    "dep_airport_name": "Brisbane International Airport",
    "dep_country": "AU",
    "dep_lat": -27.3842,
    "dep_lon": 153.117,
    "arr_airport_icao": "YCCA",
    "arr_airport_name": "Chinchilla Airport",
    "arr_country": "AU",
    "arr_lat": -26.775,
    "arr_lon": 150.617,
    "first_seen": 1781755561,
    "last_seen": 1781758087,
    "airline": "RXA",
    "departure_time": "2026-06-18 04:06 UTC",
    "arrival_time": "2026-06-18 04:48 UTC",
    "duration_minutes": 42,
    "duration_str": "42m",
    "distance_km": 256.6,
    "co2_kg": 4426.5
  },
  {
    "icao24": "7c81dc",
    "callsign": "RXA6133",
    "dep_airport_icao": "YSSY",
    "dep_airport_name": "Sydney Kingsford Smith International Airport",
    "dep_country": "AU",
    "dep_lat": -33.9461,
    "dep_lon": 151.177,
    "arr_airport_icao": "YBUY",
    "arr_airport_name": "Bunyan Airfield",
    "arr_country": "AU",
    "arr_lat": -36.1342,
    "arr_lon": 149.13198,
    "first_seen": 1781757532,
    "last_seen": 1781759756,
    "airline": "RXA",
    "departure_time": "2026-06-18 04:38 UTC",
    "arrival_time": "2026-06-18 05:15 UTC",
    "duration_minutes": 37,
    "duration_str": "37m",
    "distance_km": 306.3,
    "co2_kg": 5284.5
  },
  {
    "icao24": "7cb067",
    "callsign": "QLK861D",
    "dep_airport_icao": "YBBN",
    "dep_airport_name": "Brisbane International Airport",
    "dep_country": "AU",
    "dep_lat": -27.3842,
    "dep_lon": 153.117,
    "arr_airport_icao": "YPFT",
    "arr_airport_name": "Cooma/Polo Flat (Unlic) Airport",
    "arr_country": "AU",
    "arr_lat": -36.23,
    "arr_lon": 149.14999,
    "first_seen": 1781753032,
    "last_seen": 1781759438,
    "airline": "QLK",
    "departure_time": "2026-06-18 03:23 UTC",
    "arrival_time": "2026-06-18 05:10 UTC",
    "duration_minutes": 106,
    "duration_str": "1h 46m",
    "distance_km": 1052.3,
    "co2_kg": 18152.7
  },
  {
    "icao24": "7cf9f8",
    "callsign": "MERL",
    "dep_airport_icao": "YHOT",
    "dep_airport_name": "Mount Hotham Airport",
    "dep_country": "AU",
    "dep_lat": -37.0475,
    "dep_lon": 147.334,
    "arr_airport_icao": "YYRM",
    "arr_airport_name": "Yarram Airport",
    "arr_country": "AU",
    "arr_lat": -38.5667,
    "arr_lon": 146.755,
    "first_seen": 1781756174,
    "last_seen": 1781758185,
    "airline": "MER",
    "departure_time": "2026-06-18 04:16 UTC",
    "arrival_time": "2026-06-18 04:49 UTC",
    "duration_minutes": 33,
    "duration_str": "33m",
    "distance_km": 176.4,
    "co2_kg": 3043.2
  },
  {
    "icao24": "800bc4",
    "callsign": "IGO183E",
    "dep_airport_icao": "VOBL",
    "dep_airport_name": "Bengaluru International Airport",
    "dep_country": "IN",
    "dep_lat": 13.1979,
    "dep_lon": 77.7063,
    "arr_airport_icao": "VE41",
    "arr_airport_name": "Giridih Airport",
    "arr_country": "IN",
    "arr_lat": 24.2019,
    "arr_lon": 86.2898,
    "first_seen": 1781751961,
    "last_seen": 1781758877,
    "airline": "IndiGo",
    "departure_time": "2026-06-18 03:06 UTC",
    "arrival_time": "2026-06-18 05:01 UTC",
    "duration_minutes": 115,
    "duration_str": "1h 55m",
    "distance_km": 1520.2,
    "co2_kg": 26223.1
  },
  {
    "icao24": "800d10",
    "callsign": "IGO6947",
    "dep_airport_icao": "VOBL",
    "dep_airport_name": "Bengaluru International Airport",
    "dep_country": "IN",
    "dep_lat": 13.1979,
    "dep_lon": 77.7063,
    "arr_airport_icao": "VIPK",
    "arr_airport_name": "Pathankot Air Force Station",
    "arr_country": "IN",
    "arr_lat": 32.2338,
    "arr_lon": 75.6346,
    "first_seen": 1781747383,
    "last_seen": 1781756653,
    "airline": "IndiGo",
    "departure_time": "2026-06-18 01:49 UTC",
    "arrival_time": "2026-06-18 04:24 UTC",
    "duration_minutes": 154,
    "duration_str": "2h 34m",
    "distance_km": 2127.2,
    "co2_kg": 36693.9
  },
  {
    "icao24": "8014af",
    "callsign": "IGO5305",
    "dep_airport_icao": "VAJJ",
    "dep_airport_name": "Juhu Aerodrome",
    "dep_country": "IN",
    "dep_lat": 19.0981,
    "dep_lon": 72.8342,
    "arr_airport_icao": "VEPU",
    "arr_airport_name": "Purnea Airport",
    "arr_country": "IN",
    "arr_lat": 25.7596,
    "arr_lon": 87.41,
    "first_seen": 1781750325,
    "last_seen": 1781757977,
    "airline": "IndiGo",
    "departure_time": "2026-06-18 02:38 UTC",
    "arrival_time": "2026-06-18 04:46 UTC",
    "duration_minutes": 127,
    "duration_str": "2h 7m",
    "distance_km": 1669.6,
    "co2_kg": 28800.4
  },
  {
    "icao24": "8014ea",
    "callsign": "LLR873",
    "dep_airport_icao": "VIDP",
    "dep_airport_name": "Indira Gandhi International Airport",
    "dep_country": "IN",
    "dep_lat": 28.5665,
    "dep_lon": 77.1031,
    "arr_airport_icao": "VIPT",
    "arr_airport_name": "Pantnagar Airport",
    "arr_country": "IN",
    "arr_lat": 29.0334,
    "arr_lon": 79.4737,
    "first_seen": 1781757119,
    "last_seen": 1781759350,
    "airline": "LLR",
    "departure_time": "2026-06-18 04:31 UTC",
    "arrival_time": "2026-06-18 05:09 UTC",
    "duration_minutes": 37,
    "duration_str": "37m",
    "distance_km": 236.8,
    "co2_kg": 4084.0
  },
  {
    "icao24": "80152f",
    "callsign": "IGO1721",
    "dep_airport_icao": "VIDP",
    "dep_airport_name": "Indira Gandhi International Airport",
    "dep_country": "IN",
    "dep_lat": 28.5665,
    "dep_lon": 77.1031,
    "arr_airport_icao": "ZGSD",
    "arr_airport_name": "Zhuhai Airport",
    "arr_country": "CN",
    "arr_lat": 22.0064,
    "arr_lon": 113.376,
    "first_seen": 1781744117,
    "last_seen": 1781761296,
    "airline": "IndiGo",
    "departure_time": "2026-06-18 00:55 UTC",
    "arrival_time": "2026-06-18 05:41 UTC",
    "duration_minutes": 286,
    "duration_str": "4h 46m",
    "distance_km": 3704.6,
    "co2_kg": 63904.1
  },
  {
    "icao24": "801861",
    "callsign": "IGO5268",
    "dep_airport_icao": "VAJJ",
    "dep_airport_name": "Juhu Aerodrome",
    "dep_country": "IN",
    "dep_lat": 19.0981,
    "dep_lon": 72.8342,
    "arr_airport_icao": "VIAM",
    "arr_airport_name": "Ambala Air Force Station",
    "arr_country": "IN",
    "arr_lat": 30.3681,
    "arr_lon": 76.8167,
    "first_seen": 1781752886,
    "last_seen": 1781759123,
    "airline": "IndiGo",
    "departure_time": "2026-06-18 03:21 UTC",
    "arrival_time": "2026-06-18 05:05 UTC",
    "duration_minutes": 103,
    "duration_str": "1h 43m",
    "distance_km": 1315.8,
    "co2_kg": 22697.6
  },
  {
    "icao24": "801864",
    "callsign": "IGO5215",
    "dep_airport_icao": "VIDP",
    "dep_airport_name": "Indira Gandhi International Airport",
    "dep_country": "IN",
    "dep_lat": 28.5665,
    "dep_lon": 77.1031,
    "arr_airport_icao": "VQ10",
    "arr_airport_name": "Yongphulla Airport",
    "arr_country": "BT",
    "arr_lat": 27.2564,
    "arr_lon": 91.5145,
    "first_seen": 1781750616,
    "last_seen": 1781757095,
    "airline": "IndiGo",
    "departure_time": "2026-06-18 02:43 UTC",
    "arrival_time": "2026-06-18 04:31 UTC",
    "duration_minutes": 107,
    "duration_str": "1h 47m",
    "distance_km": 1422.7,
    "co2_kg": 24540.9
  },
  {
    "icao24": "840cd8",
    "callsign": "JJP583",
    "dep_airport_icao": "RJAF",
    "dep_airport_name": "Matsumoto Airport",
    "dep_country": "JP",
    "dep_lat": 36.1668,
    "dep_lon": 137.923,
    "arr_airport_icao": "RJOZ",
    "arr_airport_name": "Ozuki Airport",
    "arr_country": "JP",
    "arr_lat": 34.0453,
    "arr_lon": 131.052,
    "first_seen": 1781756348,
    "last_seen": 1781758964,
    "airline": "JJP",
    "departure_time": "2026-06-18 04:19 UTC",
    "arrival_time": "2026-06-18 05:02 UTC",
    "duration_minutes": 43,
    "duration_str": "43m",
    "distance_km": 667.9,
    "co2_kg": 11520.8
  },
  {
    "icao24": "841794",
    "callsign": "JJP423",
    "dep_airport_icao": "RJAA",
    "dep_airport_name": "Narita International Airport",
    "dep_country": "JP",
    "dep_lat": 35.7647,
    "dep_lon": 140.386,
    "arr_airport_icao": "RJBD",
    "arr_airport_name": "Nanki Shirahama Airport",
    "arr_country": "JP",
    "arr_lat": 33.6622,
    "arr_lon": 135.364,
    "first_seen": 1781754011,
    "last_seen": 1781756927,
    "airline": "JJP",
    "departure_time": "2026-06-18 03:40 UTC",
    "arrival_time": "2026-06-18 04:28 UTC",
    "duration_minutes": 48,
    "duration_str": "48m",
    "distance_km": 515.0,
    "co2_kg": 8884.4
  },
  {
    "icao24": "846910",
    "callsign": "ANA295",
    "dep_airport_icao": "RJTT",
    "dep_airport_name": "Tokyo International Airport",
    "dep_country": "JP",
    "dep_lat": 35.5523,
    "dep_lon": 139.78,
    "arr_airport_icao": "RJBT",
    "arr_airport_name": "Tajima Airport",
    "arr_country": "JP",
    "arr_lat": 35.5128,
    "arr_lon": 134.787,
    "first_seen": 1781756766,
    "last_seen": 1781759429,
    "airline": "All Nippon Airways",
    "departure_time": "2026-06-18 04:26 UTC",
    "arrival_time": "2026-06-18 05:10 UTC",
    "duration_minutes": 44,
    "duration_str": "44m",
    "distance_km": 451.8,
    "co2_kg": 7793.3
  },
  {
    "icao24": "85186a",
    "callsign": "JAL665",
    "dep_airport_icao": "RJTT",
    "dep_airport_name": "Tokyo International Airport",
    "dep_country": "JP",
    "dep_lat": 35.5523,
    "dep_lon": 139.78,
    "arr_airport_icao": "RJOI",
    "arr_airport_name": "Iwakuni Marine Corps Air Station",
    "arr_country": "JP",
    "arr_lat": 34.1439,
    "arr_lon": 132.23599,
    "first_seen": 1781753586,
    "last_seen": 1781757373,
    "airline": "Japan Airlines",
    "departure_time": "2026-06-18 03:33 UTC",
    "arrival_time": "2026-06-18 04:36 UTC",
    "duration_minutes": 63,
    "duration_str": "1h 3m",
    "distance_km": 705.8,
    "co2_kg": 12175.3
  },
  {
    "icao24": "862d50",
    "callsign": "JAL609",
    "dep_airport_icao": "RJTT",
    "dep_airport_name": "Tokyo International Airport",
    "dep_country": "JP",
    "dep_lat": 35.5523,
    "dep_lon": 139.78,
    "arr_airport_icao": "RJFS",
    "arr_airport_name": "Saga Airport",
    "arr_country": "JP",
    "arr_lat": 33.1497,
    "arr_lon": 130.302,
    "first_seen": 1781754541,
    "last_seen": 1781759253,
    "airline": "Japan Airlines",
    "departure_time": "2026-06-18 03:49 UTC",
    "arrival_time": "2026-06-18 05:07 UTC",
    "duration_minutes": 78,
    "duration_str": "1h 18m",
    "distance_km": 909.7,
    "co2_kg": 15693.1
  },
  {
    "icao24": "86808a",
    "callsign": "SKY011",
    "dep_airport_icao": "RJTT",
    "dep_airport_name": "Tokyo International Airport",
    "dep_country": "JP",
    "dep_lat": 35.5523,
    "dep_lon": 139.78,
    "arr_airport_icao": "RJOZ",
    "arr_airport_name": "Ozuki Airport",
    "arr_country": "JP",
    "arr_lat": 34.0453,
    "arr_lon": 131.052,
    "first_seen": 1781752397,
    "last_seen": 1781756624,
    "airline": "SKY",
    "departure_time": "2026-06-18 03:13 UTC",
    "arrival_time": "2026-06-18 04:23 UTC",
    "duration_minutes": 70,
    "duration_str": "1h 10m",
    "distance_km": 814.1,
    "co2_kg": 14042.7
  },
  {
    "icao24": "88044f",
    "callsign": "AIQ3923",
    "dep_airport_icao": "VTBD",
    "dep_airport_name": "Don Mueang International Airport",
    "dep_country": "TH",
    "dep_lat": 13.9126,
    "dep_lon": 100.607,
    "arr_airport_icao": "VTPT",
    "arr_airport_name": "Tak Airport",
    "arr_country": "TH",
    "arr_lat": 16.896,
    "arr_lon": 99.2533,
    "first_seen": 1781756824,
    "last_seen": 1781758606,
    "airline": "AIQ",
    "departure_time": "2026-06-18 04:27 UTC",
    "arrival_time": "2026-06-18 04:56 UTC",
    "duration_minutes": 29,
    "duration_str": "29m",
    "distance_km": 362.1,
    "co2_kg": 6245.9
  },
  {
    "icao24": "88140b",
    "callsign": "MTNG03",
    "dep_airport_icao": "VTBK",
    "dep_airport_name": "Kamphaeng Saen Airport",
    "dep_country": "TH",
    "dep_lat": 14.102,
    "dep_lon": 99.9172,
    "arr_airport_icao": "VTPI",
    "arr_airport_name": "Takhli Airport",
    "arr_country": "TH",
    "arr_lat": 15.2773,
    "arr_lon": 100.296,
    "first_seen": 1781757245,
    "last_seen": 1781758221,
    "airline": "MTN",
    "departure_time": "2026-06-18 04:34 UTC",
    "arrival_time": "2026-06-18 04:50 UTC",
    "duration_minutes": 16,
    "duration_str": "16m",
    "distance_km": 136.9,
    "co2_kg": 2361.4
  },
  {
    "icao24": "88140c",
    "callsign": "MTBLUE",
    "dep_airport_icao": "VTBK",
    "dep_airport_name": "Kamphaeng Saen Airport",
    "dep_country": "TH",
    "dep_lat": 14.102,
    "dep_lon": 99.9172,
    "arr_airport_icao": "VTPR",
    "arr_airport_name": "Photharam Airport",
    "arr_country": "TH",
    "arr_lat": 13.6686,
    "arr_lon": 99.7314,
    "first_seen": 1781757223,
    "last_seen": 1781758588,
    "airline": "MTB",
    "departure_time": "2026-06-18 04:33 UTC",
    "arrival_time": "2026-06-18 04:56 UTC",
    "duration_minutes": 22,
    "duration_str": "22m",
    "distance_km": 52.2,
    "co2_kg": 900.4
  },
  {
    "icao24": "884364",
    "callsign": "BKP305",
    "dep_airport_icao": "VTBS",
    "dep_airport_name": "Suvarnabhumi Airport",
    "dep_country": "TH",
    "dep_lat": 13.6811,
    "dep_lon": 100.747,
    "arr_airport_icao": "VTBW",
    "arr_airport_name": "Watthana Nakhon Airport",
    "arr_country": "TH",
    "arr_lat": 13.7688,
    "arr_lon": 102.315,
    "first_seen": 1781757986,
    "last_seen": 1781759689,
    "airline": "BKP",
    "departure_time": "2026-06-18 04:46 UTC",
    "arrival_time": "2026-06-18 05:14 UTC",
    "duration_minutes": 28,
    "duration_str": "28m",
    "distance_km": 169.7,
    "co2_kg": 2926.6
  },
  {
    "icao24": "88596d",
    "callsign": "TVJ220",
    "dep_airport_icao": "VTBS",
    "dep_airport_name": "Suvarnabhumi Airport",
    "dep_country": "TH",
    "dep_lat": 13.6811,
    "dep_lon": 100.747,
    "arr_airport_icao": "VTUJ",
    "arr_airport_name": "Surin Airport",
    "arr_country": "TH",
    "arr_lat": 14.8683,
    "arr_lon": 103.498,
    "first_seen": 1781757070,
    "last_seen": 1781758680,
    "airline": "TVJ",
    "departure_time": "2026-06-18 04:31 UTC",
    "arrival_time": "2026-06-18 04:58 UTC",
    "duration_minutes": 26,
    "duration_str": "26m",
    "distance_km": 324.5,
    "co2_kg": 5597.8
  },
  {
    "icao24": "8a01e0",
    "callsign": "GIA184",
    "dep_airport_icao": "WIII",
    "dep_airport_name": "Soekarno-Hatta International Airport",
    "dep_country": "ID",
    "dep_lat": -6.12557,
    "dep_lon": 106.656,
    "arr_airport_icao": "WIML",
    "arr_airport_name": "Kisaran Airport",
    "arr_country": "ID",
    "arr_lat": 2.97379,
    "arr_lon": 99.601,
    "first_seen": 1781751488,
    "last_seen": 1781757165,
    "airline": "Garuda Indonesia",
    "departure_time": "2026-06-18 02:58 UTC",
    "arrival_time": "2026-06-18 04:32 UTC",
    "duration_minutes": 94,
    "duration_str": "1h 34m",
    "distance_km": 1279.6,
    "co2_kg": 22073.2
  },
  {
    "icao24": "8a02ca",
    "callsign": "AWQ178",
    "dep_airport_icao": "WIII",
    "dep_airport_name": "Soekarno-Hatta International Airport",
    "dep_country": "ID",
    "dep_lat": -6.12557,
    "dep_lon": 106.656,
    "arr_airport_icao": "WIAJ",
    "arr_airport_name": "Semplak Airport",
    "arr_country": "ID",
    "arr_lat": -6.54028,
    "arr_lon": 106.75528,
    "first_seen": 1781758984,
    "last_seen": 1781759801,
    "airline": "AWQ",
    "departure_time": "2026-06-18 05:03 UTC",
    "arrival_time": "2026-06-18 05:16 UTC",
    "duration_minutes": 13,
    "duration_str": "13m",
    "distance_km": 47.4,
    "co2_kg": 817.7
  },
  {
    "icao24": "a0e23b",
    "callsign": "N156U",
    "dep_airport_icao": "KLGU",
    "dep_airport_name": "Logan-Cache Airport",
    "dep_country": "US",
    "dep_lat": 41.791771,
    "dep_lon": -111.851647,
    "arr_airport_icao": "KU14",
    "arr_airport_name": "Nephi Municipal Airport",
    "arr_country": "US",
    "arr_lat": 39.736583,
    "arr_lon": -111.870056,
    "first_seen": 1781755831,
    "last_seen": 1781759718,
    "airline": "",
    "departure_time": "2026-06-18 04:10 UTC",
    "arrival_time": "2026-06-18 05:15 UTC",
    "duration_minutes": 64,
    "duration_str": "1h 4m",
    "distance_km": 228.5,
    "co2_kg": 3942.2
  },
  {
    "icao24": "a1226e",
    "callsign": "AAL3156",
    "dep_airport_icao": "KCLT",
    "dep_airport_name": "Charlotte/Douglas International Airport",
    "dep_country": "US",
    "dep_lat": 35.213187,
    "dep_lon": -80.951379,
    "arr_airport_icao": "KDEN",
    "arr_airport_name": "Denver International Airport",
    "arr_country": "US",
    "arr_lat": 39.861667,
    "arr_lon": -104.673167,
    "first_seen": 1781746867,
    "last_seen": 1781757554,
    "airline": "American Airlines",
    "departure_time": "2026-06-18 01:41 UTC",
    "arrival_time": "2026-06-18 04:39 UTC",
    "duration_minutes": 178,
    "duration_str": "2h 58m",
    "distance_km": 2147.5,
    "co2_kg": 37045.2
  },
  {
    "icao24": "a12275",
    "callsign": "N172UZ",
    "dep_airport_icao": "KOGD",
    "dep_airport_name": "Ogden-Hinckley Airport",
    "dep_country": "US",
    "dep_lat": 41.19507,
    "dep_lon": -112.012195,
    "arr_airport_icao": "KU14",
    "arr_airport_name": "Nephi Municipal Airport",
    "arr_country": "US",
    "arr_lat": 39.736583,
    "arr_lon": -111.870056,
    "first_seen": 1781754695,
    "last_seen": 1781757722,
    "airline": "",
    "departure_time": "2026-06-18 03:51 UTC",
    "arrival_time": "2026-06-18 04:42 UTC",
    "duration_minutes": 50,
    "duration_str": "50m",
    "distance_km": 162.6,
    "co2_kg": 2805.2
  },
  {
    "icao24": "a146a2",
    "callsign": "XCN81",
    "dep_airport_icao": "KGEG",
    "dep_airport_name": "Spokane International Airport",
    "dep_country": "US",
    "dep_lat": 47.619028,
    "dep_lon": -117.535222,
    "arr_airport_icao": "K1S5",
    "arr_airport_name": "Sunnyside Municipal Airport",
    "arr_country": "US",
    "arr_lat": 46.327072,
    "arr_lon": -119.970362,
    "first_seen": 1781759767,
    "last_seen": 1781761865,
    "airline": "XCN",
    "departure_time": "2026-06-18 05:16 UTC",
    "arrival_time": "2026-06-18 05:51 UTC",
    "duration_minutes": 34,
    "duration_str": "34m",
    "distance_km": 234.0,
    "co2_kg": 4036.8
  },
  {
    "icao24": "a21ad6",
    "callsign": "N2348K",
    "dep_airport_icao": "UT99",
    "dep_airport_name": "UT99",
    "dep_country": "",
    "dep_lat": null,
    "dep_lon": null,
    "arr_airport_icao": "KENV",
    "arr_airport_name": "Wendover Airport",
    "arr_country": "US",
    "arr_lat": 40.718725,
    "arr_lon": -114.028674,
    "first_seen": 1781756526,
    "last_seen": 1781762362,
    "airline": "",
    "departure_time": "2026-06-18 04:22 UTC",
    "arrival_time": "2026-06-18 05:59 UTC",
    "duration_minutes": 97,
    "duration_str": "1h 37m",
    "distance_km": 0.0,
    "co2_kg": 0.0
  },
  {
    "icao24": "a24a31",
    "callsign": "MXY6814",
    "dep_airport_icao": "KDAL",
    "dep_airport_name": "Dallas Love Field",
    "dep_country": "US",
    "dep_lat": 32.845945,
    "dep_lon": -96.850877,
    "arr_airport_icao": "KIAD",
    "arr_airport_name": "Washington Dulles International Airport",
    "arr_country": "US",
    "arr_lat": 38.947456,
    "arr_lon": -77.459929,
    "first_seen": 1781747890,
    "last_seen": 1781756877,
    "airline": "MXY",
    "departure_time": "2026-06-18 01:58 UTC",
    "arrival_time": "2026-06-18 04:27 UTC",
    "duration_minutes": 149,
    "duration_str": "2h 29m",
    "distance_km": 1869.1,
    "co2_kg": 32242.5
  },
  {
    "icao24": "a25b66",
    "callsign": "MXY758",
    "dep_airport_icao": "KPVD",
    "dep_airport_name": "Rhode Island Tf Green International Airport",
    "dep_country": "US",
    "dep_lat": 41.722333,
    "dep_lon": -71.427722,
    "arr_airport_icao": "KDEN",
    "arr_airport_name": "Denver International Airport",
    "arr_country": "US",
    "arr_lat": 39.861667,
    "arr_lon": -104.673167,
    "first_seen": 1781743181,
    "last_seen": 1781758721,
    "airline": "MXY",
    "departure_time": "2026-06-18 00:39 UTC",
    "arrival_time": "2026-06-18 04:58 UTC",
    "duration_minutes": 259,
    "duration_str": "4h 19m",
    "distance_km": 2789.0,
    "co2_kg": 48109.7
  },
  {
    "icao24": "a3ef25",
    "callsign": "N3524F",
    "dep_airport_icao": "KOGD",
    "dep_airport_name": "Ogden-Hinckley Airport",
    "dep_country": "US",
    "dep_lat": 41.19507,
    "dep_lon": -112.012195,
    "arr_airport_icao": "KU10",
    "arr_airport_name": "Preston Airport",
    "arr_country": "US",
    "arr_lat": 42.106936,
    "arr_lon": -111.912571,
    "first_seen": 1781759595,
    "last_seen": 1781761217,
    "airline": "",
    "departure_time": "2026-06-18 05:13 UTC",
    "arrival_time": "2026-06-18 05:40 UTC",
    "duration_minutes": 27,
    "duration_str": "27m",
    "distance_km": 101.7,
    "co2_kg": 1754.9
  },
  {
    "icao24": "a5ee12",
    "callsign": "N481U",
    "dep_airport_icao": "PANC",
    "dep_airport_name": "Ted Stevens Anchorage International Airport",
    "dep_country": "US",
    "dep_lat": 61.174085,
    "dep_lon": -149.998138,
    "arr_airport_icao": "PABV",
    "arr_airport_name": "Birchwood Airport",
    "arr_country": "US",
    "arr_lat": 61.416088,
    "arr_lon": -149.50831,
    "first_seen": 1781760322,
    "last_seen": 1781761338,
    "airline": "",
    "departure_time": "2026-06-18 05:25 UTC",
    "arrival_time": "2026-06-18 05:42 UTC",
    "duration_minutes": 16,
    "duration_str": "16m",
    "distance_km": 37.5,
    "co2_kg": 647.4
  },
  {
    "icao24": "a614d0",
    "callsign": "N491LG",
    "dep_airport_icao": "CD28",
    "dep_airport_name": "Tall Timber Airport",
    "dep_country": "US",
    "dep_lat": 39.643883,
    "dep_lon": -105.267633,
    "arr_airport_icao": "CD28",
    "arr_airport_name": "Tall Timber Airport",
    "arr_country": "US",
    "arr_lat": 39.643883,
    "arr_lon": -105.267633,
    "first_seen": 1781755401,
    "last_seen": 1781756816,
    "airline": "",
    "departure_time": "2026-06-18 04:03 UTC",
    "arrival_time": "2026-06-18 04:26 UTC",
    "duration_minutes": 23,
    "duration_str": "23m",
    "distance_km": 0.0,
    "co2_kg": 0.0
  },
  {
    "icao24": "a6e80e",
    "callsign": "FENIX44",
    "dep_airport_icao": "KWSD",
    "dep_airport_name": "KWSD",
    "dep_country": "",
    "dep_lat": null,
    "dep_lon": null,
    "arr_airport_icao": "KWSD",
    "arr_airport_name": "KWSD",
    "arr_country": "",
    "arr_lat": null,
    "arr_lon": null,
    "first_seen": 1781757236,
    "last_seen": 1781758761,
    "airline": "FEN",
    "departure_time": "2026-06-18 04:33 UTC",
    "arrival_time": "2026-06-18 04:59 UTC",
    "duration_minutes": 25,
    "duration_str": "25m",
    "distance_km": 0.0,
    "co2_kg": 0.0
  },
  {
    "icao24": "a71ab4",
    "callsign": "N557PC",
    "dep_airport_icao": "NV97",
    "dep_airport_name": "Desert Creek Airport",
    "dep_country": "US",
    "dep_lat": 38.684167,
    "dep_lon": -119.322222,
    "arr_airport_icao": "KA34",
    "arr_airport_name": "Dayton Valley Airpark",
    "arr_country": "US",
    "arr_lat": 39.238424,
    "arr_lon": -119.555455,
    "first_seen": 1781756159,
    "last_seen": 1781756777,
    "airline": "",
    "departure_time": "2026-06-18 04:15 UTC",
    "arrival_time": "2026-06-18 04:26 UTC",
    "duration_minutes": 10,
    "duration_str": "10m",
    "distance_km": 64.8,
    "co2_kg": 1118.6
  },
  {
    "icao24": "abe6f4",
    "callsign": "N866US",
    "dep_airport_icao": "KBMC",
    "dep_airport_name": "Brigham City Regional Airport",
    "dep_country": "US",
    "dep_lat": 41.554306,
    "dep_lon": -112.06225,
    "arr_airport_icao": "KU14",
    "arr_airport_name": "Nephi Municipal Airport",
    "arr_country": "US",
    "arr_lat": 39.736583,
    "arr_lon": -111.870056,
    "first_seen": 1781755005,
    "last_seen": 1781759155,
    "airline": "",
    "departure_time": "2026-06-18 03:56 UTC",
    "arrival_time": "2026-06-18 05:05 UTC",
    "duration_minutes": 69,
    "duration_str": "1h 9m",
    "distance_km": 202.8,
    "co2_kg": 3497.8
  },
  {
    "icao24": "acdbee",
    "callsign": "AAL2025",
    "dep_airport_icao": "KMIA",
    "dep_airport_name": "Miami International Airport",
    "dep_country": "US",
    "dep_lat": 25.795361,
    "dep_lon": -80.290116,
    "arr_airport_icao": "KLAS",
    "arr_airport_name": "Harry Reid International Airport",
    "arr_country": "US",
    "arr_lat": 36.080343,
    "arr_lon": -115.152449,
    "first_seen": 1781742933,
    "last_seen": 1781759171,
    "airline": "American Airlines",
    "departure_time": "2026-06-18 00:35 UTC",
    "arrival_time": "2026-06-18 05:06 UTC",
    "duration_minutes": 270,
    "duration_str": "4h 30m",
    "distance_km": 3494.1,
    "co2_kg": 60273.7
  },
  {
    "icao24": "c81959",
    "callsign": "ANZ317L",
    "dep_airport_icao": "NZWN",
    "dep_airport_name": "Wellington International Airport",
    "dep_country": "NZ",
    "dep_lat": -41.3272,
    "dep_lon": 174.80499,
    "arr_airport_icao": "NZWB",
    "arr_airport_name": "Woodbourne Airport",
    "arr_country": "NZ",
    "arr_lat": -41.5183,
    "arr_lon": 173.87,
    "first_seen": 1781757995,
    "last_seen": 1781758964,
    "airline": "ANZ",
    "departure_time": "2026-06-18 04:46 UTC",
    "arrival_time": "2026-06-18 05:02 UTC",
    "duration_minutes": 16,
    "duration_str": "16m",
    "distance_km": 80.8,
    "co2_kg": 1393.8
  },
  {
    "icao24": "c81ac0",
    "callsign": "ANZ270L",
    "dep_airport_icao": "NZAA",
    "dep_airport_name": "Auckland International Airport",
    "dep_country": "NZ",
    "dep_lat": -37.0081,
    "dep_lon": 174.79201,
    "arr_airport_icao": "NZKO",
    "arr_airport_name": "Kaikohe Airport",
    "arr_country": "NZ",
    "arr_lat": -35.4511,
    "arr_lon": 173.817,
    "first_seen": 1781756655,
    "last_seen": 1781758163,
    "airline": "ANZ",
    "departure_time": "2026-06-18 04:24 UTC",
    "arrival_time": "2026-06-18 04:49 UTC",
    "duration_minutes": 25,
    "duration_str": "25m",
    "distance_km": 194.0,
    "co2_kg": 3345.8
  },
  {
    "icao24": "c82336",
    "callsign": "ANZ852M",
    "dep_airport_icao": "NZCH",
    "dep_airport_name": "Christchurch International Airport",
    "dep_country": "NZ",
    "dep_lat": -43.4894,
    "dep_lon": 172.532,
    "arr_airport_icao": "NZHR",
    "arr_airport_name": "Hanmer Springs Airport",
    "arr_country": "NZ",
    "arr_lat": -42.5508,
    "arr_lon": 172.827,
    "first_seen": 1781756621,
    "last_seen": 1781757763,
    "airline": "ANZ",
    "departure_time": "2026-06-18 04:23 UTC",
    "arrival_time": "2026-06-18 04:42 UTC",
    "duration_minutes": 19,
    "duration_str": "19m",
    "distance_km": 107.1,
    "co2_kg": 1847.3
  },
  {
    "icao24": "e48c4c",
    "callsign": "TAM3872",
    "dep_airport_icao": "SBGR",
    "dep_airport_name": "Guarulhos - Governador Andre Franco Montoro International Airport",
    "dep_country": "BR",
    "dep_lat": -23.43556,
    "dep_lon": -46.47306,
    "arr_airport_icao": "SSXU",
    "arr_airport_name": "Fazenda Fartura Airport",
    "arr_country": "BR",
    "arr_lat": -3.15778,
    "arr_lon": -48.54,
    "first_seen": 1781746813,
    "last_seen": 1781756686,
    "airline": "LATAM Airlines",
    "departure_time": "2026-06-18 01:40 UTC",
    "arrival_time": "2026-06-18 04:24 UTC",
    "duration_minutes": 164,
    "duration_str": "2h 44m",
    "distance_km": 2265.7,
    "co2_kg": 39083.6
  }
]